Workbook

Sheet Summary
A1: Hyperscale data center siting model - six US candidate markets
A2: Portfolio project built from public sources as of 7 Oct 2026. Not employer data and not investment or legal advice. Change the scenario below; every table recalculates.
A4: Scenario (pick one) | C4: Base
A5: ="Top-ranked under '"&C4&"': "&INDEX(Scoring!$C$4:$H$4,MATCH(1,Scoring!$C$34:$H$34,0))&" ("&TEXT(MAX(Scoring!$C$33:$H$33),"0.0")&" / 100)" -> Top-ranked under 'Base': Dallas-Fort Worth, TX (72.5 / 100)
A7: Results for selected scenario
A8: Market | B8: Weighted score | C8: Rank
A9: Seattle / Quincy, WA | B9: =Scoring!C33 -> 61.844745 | C9: =Scoring!C34 -> 2
A10: Hillsboro / Portland, OR | B10: =Scoring!D33 -> 29.72924 | C10: =Scoring!D34 -> 6
A11: Phoenix, AZ | B11: =Scoring!E33 -> 41.139836 | C11: =Scoring!E34 -> 4
A12: Northern Virginia | B12: =Scoring!F33 -> 40.603329 | C12: =Scoring!F34 -> 5
A13: Dallas-Fort Worth, TX | B13: =Scoring!G33 -> 72.525121 | C13: =Scoring!G34 -> 1
A14: Columbus, OH | B14: =Scoring!H33 -> 47.326373 | C14: =Scoring!H34 -> 3
A16: Ranked list
A17: Rank | B17: Market | C17: Score
A18: 1 | B18: =INDEX($A$9:$A$14,MATCH(A18,$C$9:$C$14,0)) -> Dallas-Fort Worth, TX | C18: =INDEX($B$9:$B$14,MATCH(A18,$C$9:$C$14,0)) -> 72.525121
A19: 2 | B19: =INDEX($A$9:$A$14,MATCH(A19,$C$9:$C$14,0)) -> Seattle / Quincy, WA | C19: =INDEX($B$9:$B$14,MATCH(A19,$C$9:$C$14,0)) -> 61.844745
A20: 3 | B20: =INDEX($A$9:$A$14,MATCH(A20,$C$9:$C$14,0)) -> Columbus, OH | C20: =INDEX($B$9:$B$14,MATCH(A20,$C$9:$C$14,0)) -> 47.326373
A21: 4 | B21: =INDEX($A$9:$A$14,MATCH(A21,$C$9:$C$14,0)) -> Phoenix, AZ | C21: =INDEX($B$9:$B$14,MATCH(A21,$C$9:$C$14,0)) -> 41.139836
A22: 5 | B22: =INDEX($A$9:$A$14,MATCH(A22,$C$9:$C$14,0)) -> Northern Virginia | C22: =INDEX($B$9:$B$14,MATCH(A22,$C$9:$C$14,0)) -> 40.603329
A23: 6 | B23: =INDEX($A$9:$A$14,MATCH(A23,$C$9:$C$14,0)) -> Hillsboro / Portland, OR | C23: =INDEX($B$9:$B$14,MATCH(A23,$C$9:$C$14,0)) -> 29.72924
A26: Category scores by market (0-100, selected scenario weights not applied)
A27: Category | B27: Seattle / Quincy, WA | C27: Hillsboro / Portland, OR | D27: Phoenix, AZ | E27: Northern Virginia | F27: Dallas-Fort Worth, TX | G27: Columbus, OH
A28: =Weights!B5 -> Power & Grid | B28: =Scoring!C25 -> 77.77439 | C28: =Scoring!D25 -> 48.963415 | D28: =Scoring!E25 -> 42.042683 | E28: =Scoring!F25 -> 11.25 | F28: =Scoring!G25 -> 81.25 | G28: =Scoring!H25 -> 26.79878
A29: =Weights!B6 -> Market & Pricing | B29: =Scoring!C26 -> 80.018261 | C29: =Scoring!D26 -> 7.0760761 | D29: =Scoring!E26 -> 60.756569 | E29: =Scoring!F26 -> 35.161405 | F29: =Scoring!G26 -> 78.961612 | G29: =Scoring!H26 -> 58.621192
A30: =Weights!B7 -> Network & Latency | B30: =Scoring!C27 -> 29.760629 | C30: =Scoring!D27 -> 37.5 | D30: =Scoring!E27 -> 48.964314 | E30: =Scoring!F27 -> 97.467064 | F30: =Scoring!G27 -> 82.148318 | G30: =Scoring!H27 -> 75
A31: =Weights!B8 -> Risk & Resilience | B31: =Scoring!C28 -> 66.25 | C31: =Scoring!D28 -> 40 | D31: =Scoring!E28 -> 17.5 | E31: =Scoring!F28 -> 50 | F31: =Scoring!G28 -> 32.5 | G31: =Scoring!H28 -> 73.75
A32: =Weights!B9 -> Policy & Incentives | B32: =Scoring!C29 -> 50 | C32: =Scoring!D29 -> 0 | D32: =Scoring!E29 -> 0 | E32: =Scoring!F29 -> 75 | F32: =Scoring!G29 -> 75 | G32: =Scoring!H29 -> 0
A33: =Weights!B10 -> Build & Operations | B33: =Scoring!C30 -> 50 | C33: =Scoring!D30 -> 62.5 | D33: =Scoring!E30 -> 37.5 | E33: =Scoring!F30 -> 50 | F33: =Scoring!G30 -> 62.5 | G33: =Scoring!H30 -> 50
A34: =Weights!B11 -> Growth Headroom | B34: =Scoring!C31 -> 25 | C34: =Scoring!D31 -> 0 | D34: =Scoring!E31 -> 60 | E34: =Scoring!F31 -> 25 | F34: =Scoring!G31 -> 85 | G34: =Scoring!H31 -> 50
A36: Model transparency
A37: ="Share of selected-scenario weight resting on analyst scores or estimates (not sourced figures): "&TEXT(SUMPRODUCT(Data!Q5:Q22,Weights!L16:L33),"0%") -> Share of selected-scenario weight resting on analyst scores or estimates (not sourced figures): 49%
A38: ="Weights check: "&IF(ABS(INDEX(Weights!C12:I12,MATCH(C4,Weights!C4:I4,0))-1)<0.00001,"selected scenario totals 100%","selected scenario does NOT total 100%") -> Weights check: selected scenario totals 100%
A40: How to read this
A41: Score = weighted average of 18 variables normalized to 0-100 (100 = best of the six). Scores are relative to these six markets only, not absolute quality.
A42: Illustrative requirement: a first phase of roughly 50-100 MW IT load, delivered in 2028-2029, hyperscale/AI workloads, willing to lease or build.
A43: Sheets: Data (inputs, sources, confidence) > Weights (scenarios) > Scoring (normalization) > Sensitivity (rank stability) > Latency, MarketFacts, Sources.
A44: Blue cells are inputs you can change; yellow cells are scenario levers. Green text links to other sheets.
A45: Biggest limits: rubric scores are judgment; broker rents/vacancies differ by date and size tier; FEMA county scores not pulled directly. See Data notes and Sources gaps.

Sheet Data
A1: Input data - 18 variables x 6 candidate markets
A2: Blue = hardcoded input from the cited source. Green = link to another sheet. Black = formula. 'Judgment share' = fraction of the row resting on analyst scores/estimates rather than sourced figures. Data as of 7 Oct 2026; sources on the Sources sheet.
A4: ID | B4: Category | C4: Variable | D4: Unit | E4: Type | F4: Better | G4: Transform | H4: Seattle / Quincy, WA | I4: Hillsboro / Portland, OR | J4: Phoenix, AZ | K4: Northern Virginia | L4: Dallas-Fort Worth, TX | M4: Columbus, OH | N4: Confidence | O4: Sources | P4: Notes / rationale | Q4: Judgment share
A5: A1 | B5: Power & Grid | C5: Industrial electricity price (state average) | D5: cents/kWh | E5: numeric | F5: lower | G5: none | H5: 6.61 | I5: 8.05 | J5: 7.9 | K5: 8.99 | L5: 6.12 | M5: 7.1 | N5: Verified (state-level) | O5: S1 | P5: EIA Electric Power Annual, 2024 data (WA, OR, AZ, VA, TX, OH). State averages: actual large-load tariffs differ (Grant PUD is far below WA avg; Oregon data-center class rose ~30% in 2026 under POWER Act, S23). EIA reports industrial prices up ~6% over the past year nationally. | Q5: 0
A6: A2 | B6: Power & Grid | C6: Time to power for a new large load | D6: months | E6: numeric | F6: lower | G6: none | H6: 48 | I6: 48 | J6: 60 | K6: 84 | L6: 36 | M6: 84 | N6: Reported + estimates | O6: S11, S12, S13, S15, S16, S20 | P6: NoVA 84 (JLL: ~7 yrs for 100 MW); Columbus 84 and Phoenix 60 (industry blog, S12); DFW 36 (reports of 24-36+ months, ERCOT batch study began Sep 2026). Seattle/Quincy and Hillsboro = ANALYST ESTIMATE of 48 (national avg is ~4 yrs per JLL; Grant PUD multi-year allocation queue; no >=5 MW free in Hillsboro). | Q6: 0.33
A7: A3 | B7: Power & Grid | C7: Large-load tariff / contract burden (5 = most burdensome) | D7: score 1-5 | E7: rubric | F7: lower | G7: none | H7: 3 | I7: 5 | J7: 4 | K7: 4 | L7: 4 | M7: 5 | N7: Analyst score | O7: S15-S18, S20, S22-S25 | P7: Rubric: take-or-pay minimums, collateral/security, cost allocation, curtailment. Columbus 5 (85% min demand, 8-12 yr terms, 180-day notice); Hillsboro 5 (Schedule 96: 20 MW+ self-funds distribution, ~90% minimums, ~30% rate rise); Phoenix 4 (APS load commitment agreements, proposed DC rate increase); NoVA 4 (new DC rate class, batch queue); DFW 4 (SB6: financial security, fees, curtailment rights); Quincy 3 (Grant PUD load limits and a large-load tariff). | Q7: 1
A8: A4 | B8: Power & Grid | C8: Grid clean-power profile (5 = cleanest) | D8: score 1-5 | E8: rubric | F8: higher | G8: none | H8: 5 | I8: 4 | J8: 3 | K8: 3 | L8: 3 | M8: 2 | N8: Analyst score | O8: S19, general knowledge | P8: Qualitative: hydro-dominated (Columbia basin) = 5; PNW mix = 4; solar/gas/nuclear AZ = 3; Dominion gas+nuclear = 3; ERCOT wind/solar/gas = 3; AEP Ohio/PJM coal+gas = 2. Replace with EIA state generation-mix data for a production version. | Q8: 1
A9: B1 | B9: Market & Pricing | C9: Colocation vacancy rate | D9: % | E9: numeric | F9: higher | G9: none | H9: 3.8 | I9: 0.21 | J9: 3 | K9: 0.24 | L9: 1.8 | M9: 0.1 | N9: Reported (mixed vintages) | O9: S2, S4, S6, S7, S8, S9, S19 | P9: NoVA 0.24 (CBRE H1'26); Hillsboro 0.21 (CBRE H1'26); DFW 1.8 (CBRE Q1'26); Columbus 0.1 (JLL 2026 via S9); Phoenix 3.0 (JLL mid-2025 - STALE, latest figure retrieved); Seattle 3.8 (aggregator S19, low reliability). | Q9: 0
A10: B2 | B10: Market & Pricing | C10: Immediately available capacity | D10: MW | E10: numeric | F10: higher | G10: log | H10: =ROUND(H12*H9/100,1) -> 28.2 | I10: 1 | J10: 31 | K10: 10.8 | L10: 39.6 | M10: =ROUND(M12*M9/100,1) -> 3.5 | N10: Reported + derived | O10: S2, S5, S8, S9 | P10: Hillsboro ~1.0 MW (CBRE YE2025; none >=5 MW contiguous); NoVA 10.8 MW (CBRE H1'26); DFW 39.6 MW (Q2'26); Phoenix 31 MW (JLL mid-2025). Seattle and Columbus DERIVED = inventory x vacancy. Log-scaled so one big number does not dominate. | Q10: 0
A11: B3 | B11: Market & Pricing | C11: Wholesale asking rent (midpoint of published range) | D11: $/kW-month | E11: numeric | F11: lower | G11: none | H11: 155 | I11: 200 | J11: 190 | K11: 212.5 | L11: 150 | M11: 145 | N11: Reported + 1 estimate | O11: S4, S5, S10 | P11: Hillsboro 175-225 (CBRE H2'25); Phoenix 170-210 (CBRE 250-500 kW); NoVA 190-235 (CBRE Q1'26, 250-500 kW); DFW 130-170 and Columbus 125-165 (JLL mid-2025, 1-5 MW tier). Seattle/Quincy = ESTIMATE of 155 (no published figure retrieved; low power cost, limited colo). Size tiers differ - treat as directional. | Q11: 0.17
A12: B4 | B12: Market & Pricing | C12: Installed colocation inventory (market depth) | D12: MW | E12: numeric | F12: higher | G12: log | H12: 742 | I12: 475.4 | J12: 1069.2 | K12: 4496.5 | L12: 1432.8 | M12: 3541 | N12: Reported (definitions differ) | O12: S2, S5, S9, S19 | P12: CBRE colocation inventory for Hillsboro, Phoenix, NoVA, DFW. Columbus figure is JLL Central Ohio (includes large self-build/hyperscale, so not like-for-like). Seattle = 742 MW per aggregator (S19). Log-scaled. | Q12: 0
A13: C1 | B13: Network & Latency | C13: Network / interconnection ecosystem (5 = best) | D13: score 1-5 | E13: rubric | F13: higher | G13: none | H13: 3 | I13: 4 | J13: 3 | K13: 5 | L13: 4 | M13: 3 | N13: Analyst score | O13: S2, S35, general knowledge | P13: NoVA 5 (world's densest interconnection hub); Hillsboro 4 (subsea landing stations, one of two West Coast sites); DFW 4 (central US hub); Seattle 3 (Westin Building strong, Quincy more limited); Phoenix 3 and Columbus 3 (growing). CBRE notes >20,000 route-miles of new fiber announced in 2026. | Q13: 1
A14: C2 | B14: Network & Latency | C14: Population-weighted estimated fiber RTT to 13 largest US metros | D14: ms (est.) | E14: numeric | F14: lower | G14: none | H14: =Latency!F31 -> 41.869701 | I14: =Latency!G31 -> 43.884383 | J14: =Latency!H31 -> 33.742767 | K14: =Latency!I31 -> 23.796483 | L14: =Latency!J31 -> 24.989366 | M14: =Latency!K31 -> 22.724553 | N14: Calculated (physics estimate) | O14: Latency sheet | P14: Great-circle distance x route factor, at ~200 km/ms in glass. Not a measured latency; edit assumptions on the Latency sheet. Real user distribution of the deployment would change this. | Q14: 0.5
A15: D1 | B15: Risk & Resilience | C15: Natural-hazard exposure (5 = highest) | D15: score 1-5 | E15: rubric | F15: lower | G15: none | H15: 2 | I15: 3 | J15: 5 | K15: 2 | L15: 5 | M15: 2 | N15: Mixed: NRI-based + analyst | O15: S29, S30, S31, S34 | P15: FEMA NRI v1.20 context: Maricopa County is among the 5 riskiest US counties (S29); Dallas County in the top 10 and top for hail in the first NRI (S30); Loudoun County scored lowest (2021 release); Grant County WA 44/100 'moderate' (derived, S31). Hillsboro and Columbus are ANALYST scores. Official county NRI composite scores could not be pulled automatically - replace with the NRI data download. | Q15: 0.67
A16: D2 | B16: Risk & Resilience | C16: Water stress (5 = extremely high) | D16: score 1-5 | E16: rubric | F16: lower | G16: none | H16: 2 | I16: 2 | J16: 5 | K16: 3 | L16: 3 | M16: 1 | N16: Mixed: WRI-based + analyst | O16: S32, S33, S34 | P16: WRI Aqueduct via S32: Phoenix 'extremely high', Northern Virginia 'medium-high (seasonal)'. Columbus: city water administrator says excess supply (S33). Texas has a statewide supply shortfall (DFW scored 3). Seattle and Hillsboro are ANALYST scores. | Q16: 0.67
A17: D3 | B17: Risk & Resilience | C17: Local approval / moratorium risk (5 = highest) | D17: score 1-5 | E17: rubric | F17: lower | G17: none | H17: 3 | I17: 5 | J17: 3 | K17: 4 | L17: 3 | M17: 3 | N17: Analyst score | O17: S2, S22, S35, S19 | P17: Hillsboro 5 (120-day moratorium Jul 2026, enterprise-zone tax limits); NoVA 4 (CBRE: land, permitting, power; community opposition); Seattle/Quincy 3 (Quincy pro-development, but Seattle proper paused >20 MVA applications in 2026); Phoenix, DFW, Columbus 3 (growing local opposition; CBRE says community acceptance now ranks with power as a constraint). | Q17: 1
A18: E1 | B18: Policy & Incentives | C18: Data-center sales-tax exemption status (5 = intact and stable) | D18: score 1-5 | E18: rubric | F18: higher | G18: none | H18: 3 | I18: 1 | J18: 1 | K18: 4 | L18: 4 | M18: 1 | N18: Verified status, analyst scale | O18: S21, S26-S28, S35 | P18: AZ: 3-year pause on new certificates (Jul 2026-Jun 2029). OH: new applications paused 27 May 2026. OR: HB 4084 temporarily restricts the enterprise-zone exemption. WA: new builds still eligible, replacement-equipment exemption repealed Jul 2026. VA: exemption survived 2026 budget fight (energy tax added). TX: intact, but repeal is reportedly a 2027 priority. | Q18: 0
A19: F1 | B19: Build & Operations | C19: Construction labor / contractor availability (5 = best) | D19: score 1-5 | E19: rubric | F19: higher | G19: none | H19: 2 | I19: 3 | J19: 4 | K19: 3 | L19: 5 | M19: 3 | N19: Analyst score (low confidence) | O19: none - judgment | P19: No sourced data. Judgment: DFW deepest trades pool; Quincy remote and thin; others competitive with heavy concurrent construction. Replace with BLS electrician/construction employment data. | Q19: 1
A20: F2 | B20: Build & Operations | C20: Climate / free-cooling suitability (5 = best) | D20: score 1-5 | E20: rubric | F20: higher | G20: none | H20: 4 | I20: 4 | J20: 1 | K20: 3 | L20: 2 | M20: 3 | N20: Analyst score | O20: general knowledge | P20: Cool/dry PNW = best; hot Phoenix = worst; humid summers in NoVA, DFW, Columbus in between. Replace with cooling-degree-day data. | Q20: 1
A21: G1 | B21: Growth Headroom | C21: Expansion headroom to 100+ MW within ~5 years (5 = best) | D21: score 1-5 | E21: rubric | F21: higher | G21: none | H21: 2 | I21: 1 | J21: 3 | K21: 2 | L21: 4 | M21: 3 | N21: Analyst score | O21: S2, S20, S24, S25, S13, S9, S16 | P21: Quincy 2 (Grant PUD requests ~900 MW vs ~350 MW uncommitted); Hillsboro 1 (no space, moratorium); Phoenix 3 (APS hasn't committed to new DC load since Jan, but 2 GW gas plant planned 2031-33); NoVA 2 (40 GW queue, earliest new blocks late 2028); DFW 4 (3.7 GW planned, 765 MW under construction); Columbus 3 (AEP pipeline cut by more than half after tariff). | Q21: 1
A22: G2 | B22: Growth Headroom | C22: Bridging / behind-the-meter power feasibility (5 = best) | D22: score 1-5 | E22: rubric | F22: higher | G22: none | H22: 2 | I22: 1 | J22: 4 | K22: 2 | L22: 5 | M22: 3 | N22: Analyst score | O22: S2, S25, S9 | P22: DFW 5 (CBRE: behind-the-meter gaining acceptance); Phoenix 4 (gas pipeline expansion, up to 1.2 GW behind-the-meter capacity); Columbus 3 (nuclear/BTM announcements); NoVA 2 (permitting; Vantage built own turbines); Quincy 2 (hydro-limited); Hillsboro 1. | Q22: 1
A24: Type: 'numeric' variables are min-max scaled across the six markets (0 = worst, 100 = best); 'rubric' variables are 1-5 scores scaled on an absolute 0-100 scale. 'log' transform applied to MW variables so one very large market does not flatten the rest.
A25: Caveat: rent and vacancy come from different brokers, size tiers and dates (see notes); treat them as directional. Rubric scores are the analyst's judgment from the evidence in the notes and on MarketFacts - change them and every sheet updates.

Sheet Weights
A1: Weights - category weights by scenario, and variable weights
A2: Blue = editable. Each scenario's category weights must total 100%. The 'Custom' column is yours to change; pick it on the Summary sheet.
A4: # | B4: Category | C4: Base | D4: Power-first | E4: Latency-first | F4: Cost-first | G4: Risk/Regulatory-first | H4: Speed-to-market | I4: Custom | J4: Selected
A5: 1 | B5: Power & Grid | C5: 0.3 | D5: 0.45 | E5: 0.2 | F5: 0.25 | G5: 0.22 | H5: 0.35 | I5: 0.3 | J5: =INDEX($C5:$I5,MATCH(Summary!$C$4,$C$4:$I$4,0)) -> 0.3
A6: 2 | B6: Market & Pricing | C6: 0.2 | D6: 0.15 | E6: 0.15 | F6: 0.3 | G6: 0.12 | H6: 0.25 | I6: 0.2 | J6: =INDEX($C6:$I6,MATCH(Summary!$C$4,$C$4:$I$4,0)) -> 0.2
A7: 3 | B7: Network & Latency | C7: 0.12 | D7: 0.08 | E7: 0.3 | F7: 0.08 | G7: 0.08 | H7: 0.1 | I7: 0.12 | J7: =INDEX($C7:$I7,MATCH(Summary!$C$4,$C$4:$I$4,0)) -> 0.12
A8: 4 | B8: Risk & Resilience | C8: 0.15 | D8: 0.12 | E8: 0.12 | F8: 0.1 | G8: 0.28 | H8: 0.08 | I8: 0.15 | J8: =INDEX($C8:$I8,MATCH(Summary!$C$4,$C$4:$I$4,0)) -> 0.15
A9: 5 | B9: Policy & Incentives | C9: 0.08 | D9: 0.06 | E9: 0.06 | F9: 0.15 | G9: 0.18 | H9: 0.06 | I9: 0.08 | J9: =INDEX($C9:$I9,MATCH(Summary!$C$4,$C$4:$I$4,0)) -> 0.08
A10: 6 | B10: Build & Operations | C10: 0.05 | D10: 0.04 | E10: 0.05 | F10: 0.04 | G10: 0.04 | H10: 0.04 | I10: 0.05 | J10: =INDEX($C10:$I10,MATCH(Summary!$C$4,$C$4:$I$4,0)) -> 0.05
A11: 7 | B11: Growth Headroom | C11: 0.1 | D11: 0.1 | E11: 0.12 | F11: 0.08 | G11: 0.08 | H11: 0.12 | I11: 0.1 | J11: =INDEX($C11:$I11,MATCH(Summary!$C$4,$C$4:$I$4,0)) -> 0.1
B12: Total | C12: =SUM(C5:C11) -> 1 | D12: =SUM(D5:D11) -> 1 | E12: =SUM(E5:E11) -> 1 | F12: =SUM(F5:F11) -> 1 | G12: =SUM(G5:G11) -> 1 | H12: =SUM(H5:H11) -> 1 | I12: =SUM(I5:I11) -> 1 | J12: =SUM(J5:J11) -> 1
B13: Check | C13: =IF(ABS(C12-1)<0.00001,"OK","NOT 100%") -> OK | D13: =IF(ABS(D12-1)<0.00001,"OK","NOT 100%") -> OK | E13: =IF(ABS(E12-1)<0.00001,"OK","NOT 100%") -> OK | F13: =IF(ABS(F12-1)<0.00001,"OK","NOT 100%") -> OK | G13: =IF(ABS(G12-1)<0.00001,"OK","NOT 100%") -> OK | H13: =IF(ABS(H12-1)<0.00001,"OK","NOT 100%") -> OK | I13: =IF(ABS(I12-1)<0.00001,"OK","NOT 100%") -> OK | J13: =IF(ABS(J12-1)<0.00001,"OK","NOT 100%") -> OK
A15: ID | B15: Variable | C15: Category | D15: Share within category | E15: Weight: Base | F15: Weight: Power-first | G15: Weight: Latency-first | H15: Weight: Cost-first | I15: Weight: Risk/Regulatory-first | J15: Weight: Speed-to-market | K15: Weight: Custom | L15: Weight: Selected
A16: A1 | B16: =Data!C5 -> Industrial electricity price (state average) | C16: =Data!B5 -> Power & Grid | D16: 0.35 | E16: =$D16*INDEX(C$5:C$11,MATCH($C16,$B$5:$B$11,0)) -> 0.105 | F16: =$D16*INDEX(D$5:D$11,MATCH($C16,$B$5:$B$11,0)) -> 0.1575 | G16: =$D16*INDEX(E$5:E$11,MATCH($C16,$B$5:$B$11,0)) -> 0.07 | H16: =$D16*INDEX(F$5:F$11,MATCH($C16,$B$5:$B$11,0)) -> 0.0875 | I16: =$D16*INDEX(G$5:G$11,MATCH($C16,$B$5:$B$11,0)) -> 0.077 | J16: =$D16*INDEX(H$5:H$11,MATCH($C16,$B$5:$B$11,0)) -> 0.1225 | K16: =$D16*INDEX(I$5:I$11,MATCH($C16,$B$5:$B$11,0)) -> 0.105 | L16: =$D16*INDEX($J$5:$J$11,MATCH($C16,$B$5:$B$11,0)) -> 0.105
A17: A2 | B17: =Data!C6 -> Time to power for a new large load | C17: =Data!B6 -> Power & Grid | D17: 0.35 | E17: =$D17*INDEX(C$5:C$11,MATCH($C17,$B$5:$B$11,0)) -> 0.105 | F17: =$D17*INDEX(D$5:D$11,MATCH($C17,$B$5:$B$11,0)) -> 0.1575 | G17: =$D17*INDEX(E$5:E$11,MATCH($C17,$B$5:$B$11,0)) -> 0.07 | H17: =$D17*INDEX(F$5:F$11,MATCH($C17,$B$5:$B$11,0)) -> 0.0875 | I17: =$D17*INDEX(G$5:G$11,MATCH($C17,$B$5:$B$11,0)) -> 0.077 | J17: =$D17*INDEX(H$5:H$11,MATCH($C17,$B$5:$B$11,0)) -> 0.1225 | K17: =$D17*INDEX(I$5:I$11,MATCH($C17,$B$5:$B$11,0)) -> 0.105 | L17: =$D17*INDEX($J$5:$J$11,MATCH($C17,$B$5:$B$11,0)) -> 0.105
A18: A3 | B18: =Data!C7 -> Large-load tariff / contract burden (5 = most burdensome) | C18: =Data!B7 -> Power & Grid | D18: 0.15 | E18: =$D18*INDEX(C$5:C$11,MATCH($C18,$B$5:$B$11,0)) -> 0.045 | F18: =$D18*INDEX(D$5:D$11,MATCH($C18,$B$5:$B$11,0)) -> 0.0675 | G18: =$D18*INDEX(E$5:E$11,MATCH($C18,$B$5:$B$11,0)) -> 0.03 | H18: =$D18*INDEX(F$5:F$11,MATCH($C18,$B$5:$B$11,0)) -> 0.0375 | I18: =$D18*INDEX(G$5:G$11,MATCH($C18,$B$5:$B$11,0)) -> 0.033 | J18: =$D18*INDEX(H$5:H$11,MATCH($C18,$B$5:$B$11,0)) -> 0.0525 | K18: =$D18*INDEX(I$5:I$11,MATCH($C18,$B$5:$B$11,0)) -> 0.045 | L18: =$D18*INDEX($J$5:$J$11,MATCH($C18,$B$5:$B$11,0)) -> 0.045
A19: A4 | B19: =Data!C8 -> Grid clean-power profile (5 = cleanest) | C19: =Data!B8 -> Power & Grid | D19: 0.15 | E19: =$D19*INDEX(C$5:C$11,MATCH($C19,$B$5:$B$11,0)) -> 0.045 | F19: =$D19*INDEX(D$5:D$11,MATCH($C19,$B$5:$B$11,0)) -> 0.0675 | G19: =$D19*INDEX(E$5:E$11,MATCH($C19,$B$5:$B$11,0)) -> 0.03 | H19: =$D19*INDEX(F$5:F$11,MATCH($C19,$B$5:$B$11,0)) -> 0.0375 | I19: =$D19*INDEX(G$5:G$11,MATCH($C19,$B$5:$B$11,0)) -> 0.033 | J19: =$D19*INDEX(H$5:H$11,MATCH($C19,$B$5:$B$11,0)) -> 0.0525 | K19: =$D19*INDEX(I$5:I$11,MATCH($C19,$B$5:$B$11,0)) -> 0.045 | L19: =$D19*INDEX($J$5:$J$11,MATCH($C19,$B$5:$B$11,0)) -> 0.045
A20: B1 | B20: =Data!C9 -> Colocation vacancy rate | C20: =Data!B9 -> Market & Pricing | D20: 0.2 | E20: =$D20*INDEX(C$5:C$11,MATCH($C20,$B$5:$B$11,0)) -> 0.04 | F20: =$D20*INDEX(D$5:D$11,MATCH($C20,$B$5:$B$11,0)) -> 0.03 | G20: =$D20*INDEX(E$5:E$11,MATCH($C20,$B$5:$B$11,0)) -> 0.03 | H20: =$D20*INDEX(F$5:F$11,MATCH($C20,$B$5:$B$11,0)) -> 0.06 | I20: =$D20*INDEX(G$5:G$11,MATCH($C20,$B$5:$B$11,0)) -> 0.024 | J20: =$D20*INDEX(H$5:H$11,MATCH($C20,$B$5:$B$11,0)) -> 0.05 | K20: =$D20*INDEX(I$5:I$11,MATCH($C20,$B$5:$B$11,0)) -> 0.04 | L20: =$D20*INDEX($J$5:$J$11,MATCH($C20,$B$5:$B$11,0)) -> 0.04
A21: B2 | B21: =Data!C10 -> Immediately available capacity | C21: =Data!B10 -> Market & Pricing | D21: 0.3 | E21: =$D21*INDEX(C$5:C$11,MATCH($C21,$B$5:$B$11,0)) -> 0.06 | F21: =$D21*INDEX(D$5:D$11,MATCH($C21,$B$5:$B$11,0)) -> 0.045 | G21: =$D21*INDEX(E$5:E$11,MATCH($C21,$B$5:$B$11,0)) -> 0.045 | H21: =$D21*INDEX(F$5:F$11,MATCH($C21,$B$5:$B$11,0)) -> 0.09 | I21: =$D21*INDEX(G$5:G$11,MATCH($C21,$B$5:$B$11,0)) -> 0.036 | J21: =$D21*INDEX(H$5:H$11,MATCH($C21,$B$5:$B$11,0)) -> 0.075 | K21: =$D21*INDEX(I$5:I$11,MATCH($C21,$B$5:$B$11,0)) -> 0.06 | L21: =$D21*INDEX($J$5:$J$11,MATCH($C21,$B$5:$B$11,0)) -> 0.06
A22: B3 | B22: =Data!C11 -> Wholesale asking rent (midpoint of published range) | C22: =Data!B11 -> Market & Pricing | D22: 0.35 | E22: =$D22*INDEX(C$5:C$11,MATCH($C22,$B$5:$B$11,0)) -> 0.07 | F22: =$D22*INDEX(D$5:D$11,MATCH($C22,$B$5:$B$11,0)) -> 0.0525 | G22: =$D22*INDEX(E$5:E$11,MATCH($C22,$B$5:$B$11,0)) -> 0.0525 | H22: =$D22*INDEX(F$5:F$11,MATCH($C22,$B$5:$B$11,0)) -> 0.105 | I22: =$D22*INDEX(G$5:G$11,MATCH($C22,$B$5:$B$11,0)) -> 0.042 | J22: =$D22*INDEX(H$5:H$11,MATCH($C22,$B$5:$B$11,0)) -> 0.0875 | K22: =$D22*INDEX(I$5:I$11,MATCH($C22,$B$5:$B$11,0)) -> 0.07 | L22: =$D22*INDEX($J$5:$J$11,MATCH($C22,$B$5:$B$11,0)) -> 0.07
A23: B4 | B23: =Data!C12 -> Installed colocation inventory (market depth) | C23: =Data!B12 -> Market & Pricing | D23: 0.15 | E23: =$D23*INDEX(C$5:C$11,MATCH($C23,$B$5:$B$11,0)) -> 0.03 | F23: =$D23*INDEX(D$5:D$11,MATCH($C23,$B$5:$B$11,0)) -> 0.0225 | G23: =$D23*INDEX(E$5:E$11,MATCH($C23,$B$5:$B$11,0)) -> 0.0225 | H23: =$D23*INDEX(F$5:F$11,MATCH($C23,$B$5:$B$11,0)) -> 0.045 | I23: =$D23*INDEX(G$5:G$11,MATCH($C23,$B$5:$B$11,0)) -> 0.018 | J23: =$D23*INDEX(H$5:H$11,MATCH($C23,$B$5:$B$11,0)) -> 0.0375 | K23: =$D23*INDEX(I$5:I$11,MATCH($C23,$B$5:$B$11,0)) -> 0.03 | L23: =$D23*INDEX($J$5:$J$11,MATCH($C23,$B$5:$B$11,0)) -> 0.03
A24: C1 | B24: =Data!C13 -> Network / interconnection ecosystem (5 = best) | C24: =Data!B13 -> Network & Latency | D24: 0.5 | E24: =$D24*INDEX(C$5:C$11,MATCH($C24,$B$5:$B$11,0)) -> 0.06 | F24: =$D24*INDEX(D$5:D$11,MATCH($C24,$B$5:$B$11,0)) -> 0.04 | G24: =$D24*INDEX(E$5:E$11,MATCH($C24,$B$5:$B$11,0)) -> 0.15 | H24: =$D24*INDEX(F$5:F$11,MATCH($C24,$B$5:$B$11,0)) -> 0.04 | I24: =$D24*INDEX(G$5:G$11,MATCH($C24,$B$5:$B$11,0)) -> 0.04 | J24: =$D24*INDEX(H$5:H$11,MATCH($C24,$B$5:$B$11,0)) -> 0.05 | K24: =$D24*INDEX(I$5:I$11,MATCH($C24,$B$5:$B$11,0)) -> 0.06 | L24: =$D24*INDEX($J$5:$J$11,MATCH($C24,$B$5:$B$11,0)) -> 0.06
A25: C2 | B25: =Data!C14 -> Population-weighted estimated fiber RTT to 13 largest US metros | C25: =Data!B14 -> Network & Latency | D25: 0.5 | E25: =$D25*INDEX(C$5:C$11,MATCH($C25,$B$5:$B$11,0)) -> 0.06 | F25: =$D25*INDEX(D$5:D$11,MATCH($C25,$B$5:$B$11,0)) -> 0.04 | G25: =$D25*INDEX(E$5:E$11,MATCH($C25,$B$5:$B$11,0)) -> 0.15 | H25: =$D25*INDEX(F$5:F$11,MATCH($C25,$B$5:$B$11,0)) -> 0.04 | I25: =$D25*INDEX(G$5:G$11,MATCH($C25,$B$5:$B$11,0)) -> 0.04 | J25: =$D25*INDEX(H$5:H$11,MATCH($C25,$B$5:$B$11,0)) -> 0.05 | K25: =$D25*INDEX(I$5:I$11,MATCH($C25,$B$5:$B$11,0)) -> 0.06 | L25: =$D25*INDEX($J$5:$J$11,MATCH($C25,$B$5:$B$11,0)) -> 0.06
A26: D1 | B26: =Data!C15 -> Natural-hazard exposure (5 = highest) | C26: =Data!B15 -> Risk & Resilience | D26: 0.35 | E26: =$D26*INDEX(C$5:C$11,MATCH($C26,$B$5:$B$11,0)) -> 0.0525 | F26: =$D26*INDEX(D$5:D$11,MATCH($C26,$B$5:$B$11,0)) -> 0.042 | G26: =$D26*INDEX(E$5:E$11,MATCH($C26,$B$5:$B$11,0)) -> 0.042 | H26: =$D26*INDEX(F$5:F$11,MATCH($C26,$B$5:$B$11,0)) -> 0.035 | I26: =$D26*INDEX(G$5:G$11,MATCH($C26,$B$5:$B$11,0)) -> 0.098 | J26: =$D26*INDEX(H$5:H$11,MATCH($C26,$B$5:$B$11,0)) -> 0.028 | K26: =$D26*INDEX(I$5:I$11,MATCH($C26,$B$5:$B$11,0)) -> 0.0525 | L26: =$D26*INDEX($J$5:$J$11,MATCH($C26,$B$5:$B$11,0)) -> 0.0525
A27: D2 | B27: =Data!C16 -> Water stress (5 = extremely high) | C27: =Data!B16 -> Risk & Resilience | D27: 0.3 | E27: =$D27*INDEX(C$5:C$11,MATCH($C27,$B$5:$B$11,0)) -> 0.045 | F27: =$D27*INDEX(D$5:D$11,MATCH($C27,$B$5:$B$11,0)) -> 0.036 | G27: =$D27*INDEX(E$5:E$11,MATCH($C27,$B$5:$B$11,0)) -> 0.036 | H27: =$D27*INDEX(F$5:F$11,MATCH($C27,$B$5:$B$11,0)) -> 0.03 | I27: =$D27*INDEX(G$5:G$11,MATCH($C27,$B$5:$B$11,0)) -> 0.084 | J27: =$D27*INDEX(H$5:H$11,MATCH($C27,$B$5:$B$11,0)) -> 0.024 | K27: =$D27*INDEX(I$5:I$11,MATCH($C27,$B$5:$B$11,0)) -> 0.045 | L27: =$D27*INDEX($J$5:$J$11,MATCH($C27,$B$5:$B$11,0)) -> 0.045
... A33: G2 | B33: =Data!C22 -> Bridging / behind-the-meter power feasibility (5 = best) | C33: =Data!B22 -> Growth Headroom | D33: 0.4 | E33: =$D33*INDEX(C$5:C$11,MATCH($C33,$B$5:$B$11,0)) -> 0.04 | F33: =$D33*INDEX(D$5:D$11,MATCH($C33,$B$5:$B$11,0)) -> 0.04 | G33: =$D33*INDEX(E$5:E$11,MATCH($C33,$B$5:$B$11,0)) -> 0.048 | H33: =$D33*INDEX(F$5:F$11,MATCH($C33,$B$5:$B$11,0)) -> 0.032 | I33: =$D33*INDEX(G$5:G$11,MATCH($C33,$B$5:$B$11,0)) -> 0.032 | J33: =$D33*INDEX(H$5:H$11,MATCH($C33,$B$5:$B$11,0)) -> 0.048 | K33: =$D33*INDEX(I$5:I$11,MATCH($C33,$B$5:$B$11,0)) -> 0.04 | L33: =$D33*INDEX($J$5:$J$11,MATCH($C33,$B$5:$B$11,0)) -> 0.04
B34: Total (must be 100%) | E34: =SUM(E16:E33) -> 1 | F34: =SUM(F16:F33) -> 1 | G34: =SUM(G16:G33) -> 1 | H34: =SUM(H16:H33) -> 1 | I34: =SUM(I16:I33) -> 1 | J34: =SUM(J16:J33) -> 1 | K34: =SUM(K16:K33) -> 1 | L34: =SUM(L16:L33) -> 1
B36: Check: shares within each category sum to 100%
B37: Power & Grid | C37: =SUMIF($C$16:$C$33,B37,$D$16:$D$33) -> 1 | D37: =IF(ABS(C37-1)<0.00001,"OK","CHECK") -> OK
B38: Market & Pricing | C38: =SUMIF($C$16:$C$33,B38,$D$16:$D$33) -> 1 | D38: =IF(ABS(C38-1)<0.00001,"OK","CHECK") -> OK
B39: Network & Latency | C39: =SUMIF($C$16:$C$33,B39,$D$16:$D$33) -> 1 | D39: =IF(ABS(C39-1)<0.00001,"OK","CHECK") -> OK
B40: Risk & Resilience | C40: =SUMIF($C$16:$C$33,B40,$D$16:$D$33) -> 1 | D40: =IF(ABS(C40-1)<0.00001,"OK","CHECK") -> OK
B41: Policy & Incentives | C41: =SUMIF($C$16:$C$33,B41,$D$16:$D$33) -> 1 | D41: =IF(ABS(C41-1)<0.00001,"OK","CHECK") -> OK
B42: Build & Operations | C42: =SUMIF($C$16:$C$33,B42,$D$16:$D$33) -> 1 | D42: =IF(ABS(C42-1)<0.00001,"OK","CHECK") -> OK
B43: Growth Headroom | C43: =SUMIF($C$16:$C$33,B43,$D$16:$D$33) -> 1 | D43: =IF(ABS(C43-1)<0.00001,"OK","CHECK") -> OK

Sheet Scoring
A1: Scoring - normalized 0-100 (100 = best of the six on that variable)
A2: Numeric variables: min-max across the six markets after optional log transform. Rubric variables: absolute (score-1)/4. Direction ('lower is better') is applied so that 100 is always best.
A4: ID | B4: Variable | C4: Seattle / Quincy, WA | D4: Hillsboro / Portland, OR | E4: Phoenix, AZ | F4: Northern Virginia | G4: Dallas-Fort Worth, TX | H4: Columbus, OH | J4: Transformed: Seattle / Quincy, WA | K4: Transformed: Hillsboro / Portland, OR | L4: Transformed: Phoenix, AZ | M4: Transformed: Northern Virginia | N4: Transformed: Dallas-Fort Worth, TX | O4: Transformed: Columbus, OH | P4: Min | Q4: Max
A5: A1 | B5: =Data!C5 -> Industrial electricity price (state average) | C5: =IF(Data!$E5="rubric",IF(Data!$F5="higher",(Data!H5-1)/4,(5-Data!H5)/4)*100,IF($Q5=$P5,50,IF(Data!$F5="higher",(J5-$P5)/($Q5-$P5),($Q5-J5)/($Q5-$P5))*100)) -> 82.926829 | D5: =IF(Data!$E5="rubric",IF(Data!$F5="higher",(Data!I5-1)/4,(5-Data!I5)/4)*100,IF($Q5=$P5,50,IF(Data!$F5="higher",(K5-$P5)/($Q5-$P5),($Q5-K5)/($Q5-$P5))*100)) -> 32.752613 | E5: =IF(Data!$E5="rubric",IF(Data!$F5="higher",(Data!J5-1)/4,(5-Data!J5)/4)*100,IF($Q5=$P5,50,IF(Data!$F5="higher",(L5-$P5)/($Q5-$P5),($Q5-L5)/($Q5-$P5))*100)) -> 37.979094 | F5: =IF(Data!$E5="rubric",IF(Data!$F5="higher",(Data!K5-1)/4,(5-Data!K5)/4)*100,IF($Q5=$P5,50,IF(Data!$F5="higher",(M5-$P5)/($Q5-$P5),($Q5-M5)/($Q5-$P5))*100)) -> 0 | G5: =IF(Data!$E5="rubric",IF(Data!$F5="higher",(Data!L5-1)/4,(5-Data!L5)/4)*100,IF($Q5=$P5,50,IF(Data!$F5="higher",(N5-$P5)/($Q5-$P5),($Q5-N5)/($Q5-$P5))*100)) -> 100 | H5: =IF(Data!$E5="rubric",IF(Data!$F5="higher",(Data!M5-1)/4,(5-Data!M5)/4)*100,IF($Q5=$P5,50,IF(Data!$F5="higher",(O5-$P5)/($Q5-$P5),($Q5-O5)/($Q5-$P5))*100)) -> 65.853659 | J5: =IF(Data!$G5="log",LN(Data!H5),Data!H5) -> 6.61 | K5: =IF(Data!$G5="log",LN(Data!I5),Data!I5) -> 8.05 | L5: =IF(Data!$G5="log",LN(Data!J5),Data!J5) -> 7.9 | M5: =IF(Data!$G5="log",LN(Data!K5),Data!K5) -> 8.99 | N5: =IF(Data!$G5="log",LN(Data!L5),Data!L5) -> 6.12 | O5: =IF(Data!$G5="log",LN(Data!M5),Data!M5) -> 7.1 | P5: =MIN(J5:O5) -> 6.12 | Q5: =MAX(J5:O5) -> 8.99
A6: A2 | B6: =Data!C6 -> Time to power for a new large load | C6: =IF(Data!$E6="rubric",IF(Data!$F6="higher",(Data!H6-1)/4,(5-Data!H6)/4)*100,IF($Q6=$P6,50,IF(Data!$F6="higher",(J6-$P6)/($Q6-$P6),($Q6-J6)/($Q6-$P6))*100)) -> 75 | D6: =IF(Data!$E6="rubric",IF(Data!$F6="higher",(Data!I6-1)/4,(5-Data!I6)/4)*100,IF($Q6=$P6,50,IF(Data!$F6="higher",(K6-$P6)/($Q6-$P6),($Q6-K6)/($Q6-$P6))*100)) -> 75 | E6: =IF(Data!$E6="rubric",IF(Data!$F6="higher",(Data!J6-1)/4,(5-Data!J6)/4)*100,IF($Q6=$P6,50,IF(Data!$F6="higher",(L6-$P6)/($Q6-$P6),($Q6-L6)/($Q6-$P6))*100)) -> 50 | F6: =IF(Data!$E6="rubric",IF(Data!$F6="higher",(Data!K6-1)/4,(5-Data!K6)/4)*100,IF($Q6=$P6,50,IF(Data!$F6="higher",(M6-$P6)/($Q6-$P6),($Q6-M6)/($Q6-$P6))*100)) -> 0 | G6: =IF(Data!$E6="rubric",IF(Data!$F6="higher",(Data!L6-1)/4,(5-Data!L6)/4)*100,IF($Q6=$P6,50,IF(Data!$F6="higher",(N6-$P6)/($Q6-$P6),($Q6-N6)/($Q6-$P6))*100)) -> 100 | H6: =IF(Data!$E6="rubric",IF(Data!$F6="higher",(Data!M6-1)/4,(5-Data!M6)/4)*100,IF($Q6=$P6,50,IF(Data!$F6="higher",(O6-$P6)/($Q6-$P6),($Q6-O6)/($Q6-$P6))*100)) -> 0 | J6: =IF(Data!$G6="log",LN(Data!H6),Data!H6) -> 48 | K6: =IF(Data!$G6="log",LN(Data!I6),Data!I6) -> 48 | L6: =IF(Data!$G6="log",LN(Data!J6),Data!J6) -> 60 | M6: =IF(Data!$G6="log",LN(Data!K6),Data!K6) -> 84 | N6: =IF(Data!$G6="log",LN(Data!L6),Data!L6) -> 36 | O6: =IF(Data!$G6="log",LN(Data!M6),Data!M6) -> 84 | P6: =MIN(J6:O6) -> 36 | Q6: =MAX(J6:O6) -> 84
A7: A3 | B7: =Data!C7 -> Large-load tariff / contract burden (5 = most burdensome) | C7: =IF(Data!$E7="rubric",IF(Data!$F7="higher",(Data!H7-1)/4,(5-Data!H7)/4)*100,IF($Q7=$P7,50,IF(Data!$F7="higher",(J7-$P7)/($Q7-$P7),($Q7-J7)/($Q7-$P7))*100)) -> 50 | D7: =IF(Data!$E7="rubric",IF(Data!$F7="higher",(Data!I7-1)/4,(5-Data!I7)/4)*100,IF($Q7=$P7,50,IF(Data!$F7="higher",(K7-$P7)/($Q7-$P7),($Q7-K7)/($Q7-$P7))*100)) -> 0 | E7: =IF(Data!$E7="rubric",IF(Data!$F7="higher",(Data!J7-1)/4,(5-Data!J7)/4)*100,IF($Q7=$P7,50,IF(Data!$F7="higher",(L7-$P7)/($Q7-$P7),($Q7-L7)/($Q7-$P7))*100)) -> 25 | F7: =IF(Data!$E7="rubric",IF(Data!$F7="higher",(Data!K7-1)/4,(5-Data!K7)/4)*100,IF($Q7=$P7,50,IF(Data!$F7="higher",(M7-$P7)/($Q7-$P7),($Q7-M7)/($Q7-$P7))*100)) -> 25 | G7: =IF(Data!$E7="rubric",IF(Data!$F7="higher",(Data!L7-1)/4,(5-Data!L7)/4)*100,IF($Q7=$P7,50,IF(Data!$F7="higher",(N7-$P7)/($Q7-$P7),($Q7-N7)/($Q7-$P7))*100)) -> 25 | H7: =IF(Data!$E7="rubric",IF(Data!$F7="higher",(Data!M7-1)/4,(5-Data!M7)/4)*100,IF($Q7=$P7,50,IF(Data!$F7="higher",(O7-$P7)/($Q7-$P7),($Q7-O7)/($Q7-$P7))*100)) -> 0 | J7: =IF(Data!$G7="log",LN(Data!H7),Data!H7) -> 3 | K7: =IF(Data!$G7="log",LN(Data!I7),Data!I7) -> 5 | L7: =IF(Data!$G7="log",LN(Data!J7),Data!J7) -> 4 | M7: =IF(Data!$G7="log",LN(Data!K7),Data!K7) -> 4 | N7: =IF(Data!$G7="log",LN(Data!L7),Data!L7) -> 4 | O7: =IF(Data!$G7="log",LN(Data!M7),Data!M7) -> 5 | P7: =MIN(J7:O7) -> 3 | Q7: =MAX(J7:O7) -> 5
A8: A4 | B8: =Data!C8 -> Grid clean-power profile (5 = cleanest) | C8: =IF(Data!$E8="rubric",IF(Data!$F8="higher",(Data!H8-1)/4,(5-Data!H8)/4)*100,IF($Q8=$P8,50,IF(Data!$F8="higher",(J8-$P8)/($Q8-$P8),($Q8-J8)/($Q8-$P8))*100)) -> 100 | D8: =IF(Data!$E8="rubric",IF(Data!$F8="higher",(Data!I8-1)/4,(5-Data!I8)/4)*100,IF($Q8=$P8,50,IF(Data!$F8="higher",(K8-$P8)/($Q8-$P8),($Q8-K8)/($Q8-$P8))*100)) -> 75 | E8: =IF(Data!$E8="rubric",IF(Data!$F8="higher",(Data!J8-1)/4,(5-Data!J8)/4)*100,IF($Q8=$P8,50,IF(Data!$F8="higher",(L8-$P8)/($Q8-$P8),($Q8-L8)/($Q8-$P8))*100)) -> 50 | F8: =IF(Data!$E8="rubric",IF(Data!$F8="higher",(Data!K8-1)/4,(5-Data!K8)/4)*100,IF($Q8=$P8,50,IF(Data!$F8="higher",(M8-$P8)/($Q8-$P8),($Q8-M8)/($Q8-$P8))*100)) -> 50 | G8: =IF(Data!$E8="rubric",IF(Data!$F8="higher",(Data!L8-1)/4,(5-Data!L8)/4)*100,IF($Q8=$P8,50,IF(Data!$F8="higher",(N8-$P8)/($Q8-$P8),($Q8-N8)/($Q8-$P8))*100)) -> 50 | H8: =IF(Data!$E8="rubric",IF(Data!$F8="higher",(Data!M8-1)/4,(5-Data!M8)/4)*100,IF($Q8=$P8,50,IF(Data!$F8="higher",(O8-$P8)/($Q8-$P8),($Q8-O8)/($Q8-$P8))*100)) -> 25 | J8: =IF(Data!$G8="log",LN(Data!H8),Data!H8) -> 5 | K8: =IF(Data!$G8="log",LN(Data!I8),Data!I8) -> 4 | L8: =IF(Data!$G8="log",LN(Data!J8),Data!J8) -> 3 | M8: =IF(Data!$G8="log",LN(Data!K8),Data!K8) -> 3 | N8: =IF(Data!$G8="log",LN(Data!L8),Data!L8) -> 3 | O8: =IF(Data!$G8="log",LN(Data!M8),Data!M8) -> 2 | P8: =MIN(J8:O8) -> 2 | Q8: =MAX(J8:O8) -> 5
A9: B1 | B9: =Data!C9 -> Colocation vacancy rate | C9: =IF(Data!$E9="rubric",IF(Data!$F9="higher",(Data!H9-1)/4,(5-Data!H9)/4)*100,IF($Q9=$P9,50,IF(Data!$F9="higher",(J9-$P9)/($Q9-$P9),($Q9-J9)/($Q9-$P9))*100)) -> 100 | D9: =IF(Data!$E9="rubric",IF(Data!$F9="higher",(Data!I9-1)/4,(5-Data!I9)/4)*100,IF($Q9=$P9,50,IF(Data!$F9="higher",(K9-$P9)/($Q9-$P9),($Q9-K9)/($Q9-$P9))*100)) -> 2.972973 | E9: =IF(Data!$E9="rubric",IF(Data!$F9="higher",(Data!J9-1)/4,(5-Data!J9)/4)*100,IF($Q9=$P9,50,IF(Data!$F9="higher",(L9-$P9)/($Q9-$P9),($Q9-L9)/($Q9-$P9))*100)) -> 78.378378 | F9: =IF(Data!$E9="rubric",IF(Data!$F9="higher",(Data!K9-1)/4,(5-Data!K9)/4)*100,IF($Q9=$P9,50,IF(Data!$F9="higher",(M9-$P9)/($Q9-$P9),($Q9-M9)/($Q9-$P9))*100)) -> 3.7837838 | G9: =IF(Data!$E9="rubric",IF(Data!$F9="higher",(Data!L9-1)/4,(5-Data!L9)/4)*100,IF($Q9=$P9,50,IF(Data!$F9="higher",(N9-$P9)/($Q9-$P9),($Q9-N9)/($Q9-$P9))*100)) -> 45.945946 | H9: =IF(Data!$E9="rubric",IF(Data!$F9="higher",(Data!M9-1)/4,(5-Data!M9)/4)*100,IF($Q9=$P9,50,IF(Data!$F9="higher",(O9-$P9)/($Q9-$P9),($Q9-O9)/($Q9-$P9))*100)) -> 0 | J9: =IF(Data!$G9="log",LN(Data!H9),Data!H9) -> 3.8 | K9: =IF(Data!$G9="log",LN(Data!I9),Data!I9) -> 0.21 | L9: =IF(Data!$G9="log",LN(Data!J9),Data!J9) -> 3 | M9: =IF(Data!$G9="log",LN(Data!K9),Data!K9) -> 0.24 | N9: =IF(Data!$G9="log",LN(Data!L9),Data!L9) -> 1.8 | O9: =IF(Data!$G9="log",LN(Data!M9),Data!M9) -> 0.1 | P9: =MIN(J9:O9) -> 0.1 | Q9: =MAX(J9:O9) -> 3.8
A10: B2 | B10: =Data!C10 -> Immediately available capacity | C10: =IF(Data!$E10="rubric",IF(Data!$F10="higher",(Data!H10-1)/4,(5-Data!H10)/4)*100,IF($Q10=$P10,50,IF(Data!$F10="higher",(J10-$P10)/($Q10-$P10),($Q10-J10)/($Q10-$P10))*100)) -> 90.771326 | D10: =IF(Data!$E10="rubric",IF(Data!$F10="higher",(Data!I10-1)/4,(5-Data!I10)/4)*100,IF($Q10=$P10,50,IF(Data!$F10="higher",(K10-$P10)/($Q10-$P10),($Q10-K10)/($Q10-$P10))*100)) -> 0 | E10: =IF(Data!$E10="rubric",IF(Data!$F10="higher",(Data!J10-1)/4,(5-Data!J10)/4)*100,IF($Q10=$P10,50,IF(Data!$F10="higher",(L10-$P10)/($Q10-$P10),($Q10-L10)/($Q10-$P10))*100)) -> 93.34457 | F10: =IF(Data!$E10="rubric",IF(Data!$F10="higher",(Data!K10-1)/4,(5-Data!K10)/4)*100,IF($Q10=$P10,50,IF(Data!$F10="higher",(M10-$P10)/($Q10-$P10),($Q10-M10)/($Q10-$P10))*100)) -> 64.68216 | G10: =IF(Data!$E10="rubric",IF(Data!$F10="higher",(Data!L10-1)/4,(5-Data!L10)/4)*100,IF($Q10=$P10,50,IF(Data!$F10="higher",(N10-$P10)/($Q10-$P10),($Q10-N10)/($Q10-$P10))*100)) -> 100 | H10: =IF(Data!$E10="rubric",IF(Data!$F10="higher",(Data!M10-1)/4,(5-Data!M10)/4)*100,IF($Q10=$P10,50,IF(Data!$F10="higher",(O10-$P10)/($Q10-$P10),($Q10-O10)/($Q10-$P10))*100)) -> 34.053307 | J10: =IF(Data!$G10="log",LN(Data!H10),Data!H10) -> 3.339322 | K10: =IF(Data!$G10="log",LN(Data!I10),Data!I10) -> 0 | L10: =IF(Data!$G10="log",LN(Data!J10),Data!J10) -> 3.4339872 | M10: =IF(Data!$G10="log",LN(Data!K10),Data!K10) -> 2.3795461 | N10: =IF(Data!$G10="log",LN(Data!L10),Data!L10) -> 3.6788291 | O10: =IF(Data!$G10="log",LN(Data!M10),Data!M10) -> 1.252763 | P10: =MIN(J10:O10) -> 0 | Q10: =MAX(J10:O10) -> 3.6788291
A11: B3 | B11: =Data!C11 -> Wholesale asking rent (midpoint of published range) | C11: =IF(Data!$E11="rubric",IF(Data!$F11="higher",(Data!H11-1)/4,(5-Data!H11)/4)*100,IF($Q11=$P11,50,IF(Data!$F11="higher",(J11-$P11)/($Q11-$P11),($Q11-J11)/($Q11-$P11))*100)) -> 85.185185 | D11: =IF(Data!$E11="rubric",IF(Data!$F11="higher",(Data!I11-1)/4,(5-Data!I11)/4)*100,IF($Q11=$P11,50,IF(Data!$F11="higher",(K11-$P11)/($Q11-$P11),($Q11-K11)/($Q11-$P11))*100)) -> 18.518519 | E11: =IF(Data!$E11="rubric",IF(Data!$F11="higher",(Data!J11-1)/4,(5-Data!J11)/4)*100,IF($Q11=$P11,50,IF(Data!$F11="higher",(L11-$P11)/($Q11-$P11),($Q11-L11)/($Q11-$P11))*100)) -> 33.333333 | F11: =IF(Data!$E11="rubric",IF(Data!$F11="higher",(Data!K11-1)/4,(5-Data!K11)/4)*100,IF($Q11=$P11,50,IF(Data!$F11="higher",(M11-$P11)/($Q11-$P11),($Q11-M11)/($Q11-$P11))*100)) -> 0 | G11: =IF(Data!$E11="rubric",IF(Data!$F11="higher",(Data!L11-1)/4,(5-Data!L11)/4)*100,IF($Q11=$P11,50,IF(Data!$F11="higher",(N11-$P11)/($Q11-$P11),($Q11-N11)/($Q11-$P11))*100)) -> 92.592593 | H11: =IF(Data!$E11="rubric",IF(Data!$F11="higher",(Data!M11-1)/4,(5-Data!M11)/4)*100,IF($Q11=$P11,50,IF(Data!$F11="higher",(O11-$P11)/($Q11-$P11),($Q11-O11)/($Q11-$P11))*100)) -> 100 | J11: =IF(Data!$G11="log",LN(Data!H11),Data!H11) -> 155 | K11: =IF(Data!$G11="log",LN(Data!I11),Data!I11) -> 200 | L11: =IF(Data!$G11="log",LN(Data!J11),Data!J11) -> 190 | M11: =IF(Data!$G11="log",LN(Data!K11),Data!K11) -> 212.5 | N11: =IF(Data!$G11="log",LN(Data!L11),Data!L11) -> 150 | O11: =IF(Data!$G11="log",LN(Data!M11),Data!M11) -> 145 | P11: =MIN(J11:O11) -> 145 | Q11: =MAX(J11:O11) -> 212.5
A12: B4 | B12: =Data!C12 -> Installed colocation inventory (market depth) | C12: =IF(Data!$E12="rubric",IF(Data!$F12="higher",(Data!H12-1)/4,(5-Data!H12)/4)*100,IF($Q12=$P12,50,IF(Data!$F12="higher",(J12-$P12)/($Q12-$P12),($Q12-J12)/($Q12-$P12))*100)) -> 19.813658 | D12: =IF(Data!$E12="rubric",IF(Data!$F12="higher",(Data!I12-1)/4,(5-Data!I12)/4)*100,IF($Q12=$P12,50,IF(Data!$F12="higher",(K12-$P12)/($Q12-$P12),($Q12-K12)/($Q12-$P12))*100)) -> 0 | E12: =IF(Data!$E12="rubric",IF(Data!$F12="higher",(Data!J12-1)/4,(5-Data!J12)/4)*100,IF($Q12=$P12,50,IF(Data!$F12="higher",(L12-$P12)/($Q12-$P12),($Q12-L12)/($Q12-$P12))*100)) -> 36.072372 | F12: =IF(Data!$E12="rubric",IF(Data!$F12="higher",(Data!K12-1)/4,(5-Data!K12)/4)*100,IF($Q12=$P12,50,IF(Data!$F12="higher",(M12-$P12)/($Q12-$P12),($Q12-M12)/($Q12-$P12))*100)) -> 100 | G12: =IF(Data!$E12="rubric",IF(Data!$F12="higher",(Data!L12-1)/4,(5-Data!L12)/4)*100,IF($Q12=$P12,50,IF(Data!$F12="higher",(N12-$P12)/($Q12-$P12),($Q12-N12)/($Q12-$P12))*100)) -> 49.100105 | H12: =IF(Data!$E12="rubric",IF(Data!$F12="higher",(Data!M12-1)/4,(5-Data!M12)/4)*100,IF($Q12=$P12,50,IF(Data!$F12="higher",(O12-$P12)/($Q12-$P12),($Q12-O12)/($Q12-$P12))*100)) -> 89.368003 | J12: =IF(Data!$G12="log",LN(Data!H12),Data!H12) -> 6.6093492 | K12: =IF(Data!$G12="log",LN(Data!I12),Data!I12) -> 6.1641566 | L12: =IF(Data!$G12="log",LN(Data!J12),Data!J12) -> 6.974666 | M12: =IF(Data!$G12="log",LN(Data!K12),Data!K12) -> 8.4110546 | N12: =IF(Data!$G12="log",LN(Data!L12),Data!L12) -> 7.2673859 | O12: =IF(Data!$G12="log",LN(Data!M12),Data!M12) -> 8.1721645 | P12: =MIN(J12:O12) -> 6.1641566 | Q12: =MAX(J12:O12) -> 8.4110546
A13: C1 | B13: =Data!C13 -> Network / interconnection ecosystem (5 = best) | C13: =IF(Data!$E13="rubric",IF(Data!$F13="higher",(Data!H13-1)/4,(5-Data!H13)/4)*100,IF($Q13=$P13,50,IF(Data!$F13="higher",(J13-$P13)/($Q13-$P13),($Q13-J13)/($Q13-$P13))*100)) -> 50 | D13: =IF(Data!$E13="rubric",IF(Data!$F13="higher",(Data!I13-1)/4,(5-Data!I13)/4)*100,IF($Q13=$P13,50,IF(Data!$F13="higher",(K13-$P13)/($Q13-$P13),($Q13-K13)/($Q13-$P13))*100)) -> 75 | E13: =IF(Data!$E13="rubric",IF(Data!$F13="higher",(Data!J13-1)/4,(5-Data!J13)/4)*100,IF($Q13=$P13,50,IF(Data!$F13="higher",(L13-$P13)/($Q13-$P13),($Q13-L13)/($Q13-$P13))*100)) -> 50 | F13: =IF(Data!$E13="rubric",IF(Data!$F13="higher",(Data!K13-1)/4,(5-Data!K13)/4)*100,IF($Q13=$P13,50,IF(Data!$F13="higher",(M13-$P13)/($Q13-$P13),($Q13-M13)/($Q13-$P13))*100)) -> 100 | G13: =IF(Data!$E13="rubric",IF(Data!$F13="higher",(Data!L13-1)/4,(5-Data!L13)/4)*100,IF($Q13=$P13,50,IF(Data!$F13="higher",(N13-$P13)/($Q13-$P13),($Q13-N13)/($Q13-$P13))*100)) -> 75 | H13: =IF(Data!$E13="rubric",IF(Data!$F13="higher",(Data!M13-1)/4,(5-Data!M13)/4)*100,IF($Q13=$P13,50,IF(Data!$F13="higher",(O13-$P13)/($Q13-$P13),($Q13-O13)/($Q13-$P13))*100)) -> 50 | J13: =IF(Data!$G13="log",LN(Data!H13),Data!H13) -> 3 | K13: =IF(Data!$G13="log",LN(Data!I13),Data!I13) -> 4 | L13: =IF(Data!$G13="log",LN(Data!J13),Data!J13) -> 3 | M13: =IF(Data!$G13="log",LN(Data!K13),Data!K13) -> 5 | N13: =IF(Data!$G13="log",LN(Data!L13),Data!L13) -> 4 | O13: =IF(Data!$G13="log",LN(Data!M13),Data!M13) -> 3 | P13: =MIN(J13:O13) -> 3 | Q13: =MAX(J13:O13) -> 5
A14: C2 | B14: =Data!C14 -> Population-weighted estimated fiber RTT to 13 largest US metros | C14: =IF(Data!$E14="rubric",IF(Data!$F14="higher",(Data!H14-1)/4,(5-Data!H14)/4)*100,IF($Q14=$P14,50,IF(Data!$F14="higher",(J14-$P14)/($Q14-$P14),($Q14-J14)/($Q14-$P14))*100)) -> 9.5212573 | D14: =IF(Data!$E14="rubric",IF(Data!$F14="higher",(Data!I14-1)/4,(5-Data!I14)/4)*100,IF($Q14=$P14,50,IF(Data!$F14="higher",(K14-$P14)/($Q14-$P14),($Q14-K14)/($Q14-$P14))*100)) -> 0 | E14: =IF(Data!$E14="rubric",IF(Data!$F14="higher",(Data!J14-1)/4,(5-Data!J14)/4)*100,IF($Q14=$P14,50,IF(Data!$F14="higher",(L14-$P14)/($Q14-$P14),($Q14-L14)/($Q14-$P14))*100)) -> 47.928627 | F14: =IF(Data!$E14="rubric",IF(Data!$F14="higher",(Data!K14-1)/4,(5-Data!K14)/4)*100,IF($Q14=$P14,50,IF(Data!$F14="higher",(M14-$P14)/($Q14-$P14),($Q14-M14)/($Q14-$P14))*100)) -> 94.934128 | G14: =IF(Data!$E14="rubric",IF(Data!$F14="higher",(Data!L14-1)/4,(5-Data!L14)/4)*100,IF($Q14=$P14,50,IF(Data!$F14="higher",(N14-$P14)/($Q14-$P14),($Q14-N14)/($Q14-$P14))*100)) -> 89.296635 | H14: =IF(Data!$E14="rubric",IF(Data!$F14="higher",(Data!M14-1)/4,(5-Data!M14)/4)*100,IF($Q14=$P14,50,IF(Data!$F14="higher",(O14-$P14)/($Q14-$P14),($Q14-O14)/($Q14-$P14))*100)) -> 100 | J14: =IF(Data!$G14="log",LN(Data!H14),Data!H14) -> 41.869701 | K14: =IF(Data!$G14="log",LN(Data!I14),Data!I14) -> 43.884383 | L14: =IF(Data!$G14="log",LN(Data!J14),Data!J14) -> 33.742767 | M14: =IF(Data!$G14="log",LN(Data!K14),Data!K14) -> 23.796483 | N14: =IF(Data!$G14="log",LN(Data!L14),Data!L14) -> 24.989366 | O14: =IF(Data!$G14="log",LN(Data!M14),Data!M14) -> 22.724553 | P14: =MIN(J14:O14) -> 22.724553 | Q14: =MAX(J14:O14) -> 43.884383
A15: D1 | B15: =Data!C15 -> Natural-hazard exposure (5 = highest) | C15: =IF(Data!$E15="rubric",IF(Data!$F15="higher",(Data!H15-1)/4,(5-Data!H15)/4)*100,IF($Q15=$P15,50,IF(Data!$F15="higher",(J15-$P15)/($Q15-$P15),($Q15-J15)/($Q15-$P15))*100)) -> 75 | D15: =IF(Data!$E15="rubric",IF(Data!$F15="higher",(Data!I15-1)/4,(5-Data!I15)/4)*100,IF($Q15=$P15,50,IF(Data!$F15="higher",(K15-$P15)/($Q15-$P15),($Q15-K15)/($Q15-$P15))*100)) -> 50 | E15: =IF(Data!$E15="rubric",IF(Data!$F15="higher",(Data!J15-1)/4,(5-Data!J15)/4)*100,IF($Q15=$P15,50,IF(Data!$F15="higher",(L15-$P15)/($Q15-$P15),($Q15-L15)/($Q15-$P15))*100)) -> 0 | F15: =IF(Data!$E15="rubric",IF(Data!$F15="higher",(Data!K15-1)/4,(5-Data!K15)/4)*100,IF($Q15=$P15,50,IF(Data!$F15="higher",(M15-$P15)/($Q15-$P15),($Q15-M15)/($Q15-$P15))*100)) -> 75 | G15: =IF(Data!$E15="rubric",IF(Data!$F15="higher",(Data!L15-1)/4,(5-Data!L15)/4)*100,IF($Q15=$P15,50,IF(Data!$F15="higher",(N15-$P15)/($Q15-$P15),($Q15-N15)/($Q15-$P15))*100)) -> 0 | H15: =IF(Data!$E15="rubric",IF(Data!$F15="higher",(Data!M15-1)/4,(5-Data!M15)/4)*100,IF($Q15=$P15,50,IF(Data!$F15="higher",(O15-$P15)/($Q15-$P15),($Q15-O15)/($Q15-$P15))*100)) -> 75 | J15: =IF(Data!$G15="log",LN(Data!H15),Data!H15) -> 2 | K15: =IF(Data!$G15="log",LN(Data!I15),Data!I15) -> 3 | L15: =IF(Data!$G15="log",LN(Data!J15),Data!J15) -> 5 | M15: =IF(Data!$G15="log",LN(Data!K15),Data!K15) -> 2 | N15: =IF(Data!$G15="log",LN(Data!L15),Data!L15) -> 5 | O15: =IF(Data!$G15="log",LN(Data!M15),Data!M15) -> 2 | P15: =MIN(J15:O15) -> 2 | Q15: =MAX(J15:O15) -> 5
A16: D2 | B16: =Data!C16 -> Water stress (5 = extremely high) | C16: =IF(Data!$E16="rubric",IF(Data!$F16="higher",(Data!H16-1)/4,(5-Data!H16)/4)*100,IF($Q16=$P16,50,IF(Data!$F16="higher",(J16-$P16)/($Q16-$P16),($Q16-J16)/($Q16-$P16))*100)) -> 75 | D16: =IF(Data!$E16="rubric",IF(Data!$F16="higher",(Data!I16-1)/4,(5-Data!I16)/4)*100,IF($Q16=$P16,50,IF(Data!$F16="higher",(K16-$P16)/($Q16-$P16),($Q16-K16)/($Q16-$P16))*100)) -> 75 | E16: =IF(Data!$E16="rubric",IF(Data!$F16="higher",(Data!J16-1)/4,(5-Data!J16)/4)*100,IF($Q16=$P16,50,IF(Data!$F16="higher",(L16-$P16)/($Q16-$P16),($Q16-L16)/($Q16-$P16))*100)) -> 0 | F16: =IF(Data!$E16="rubric",IF(Data!$F16="higher",(Data!K16-1)/4,(5-Data!K16)/4)*100,IF($Q16=$P16,50,IF(Data!$F16="higher",(M16-$P16)/($Q16-$P16),($Q16-M16)/($Q16-$P16))*100)) -> 50 | G16: =IF(Data!$E16="rubric",IF(Data!$F16="higher",(Data!L16-1)/4,(5-Data!L16)/4)*100,IF($Q16=$P16,50,IF(Data!$F16="higher",(N16-$P16)/($Q16-$P16),($Q16-N16)/($Q16-$P16))*100)) -> 50 | H16: =IF(Data!$E16="rubric",IF(Data!$F16="higher",(Data!M16-1)/4,(5-Data!M16)/4)*100,IF($Q16=$P16,50,IF(Data!$F16="higher",(O16-$P16)/($Q16-$P16),($Q16-O16)/($Q16-$P16))*100)) -> 100 | J16: =IF(Data!$G16="log",LN(Data!H16),Data!H16) -> 2 | K16: =IF(Data!$G16="log",LN(Data!I16),Data!I16) -> 2 | L16: =IF(Data!$G16="log",LN(Data!J16),Data!J16) -> 5 | M16: =IF(Data!$G16="log",LN(Data!K16),Data!K16) -> 3 | N16: =IF(Data!$G16="log",LN(Data!L16),Data!L16) -> 3 | O16: =IF(Data!$G16="log",LN(Data!M16),Data!M16) -> 1 | P16: =MIN(J16:O16) -> 1 | Q16: =MAX(J16:O16) -> 5
... A22: G2 | B22: =Data!C22 -> Bridging / behind-the-meter power feasibility (5 = best) | C22: =IF(Data!$E22="rubric",IF(Data!$F22="higher",(Data!H22-1)/4,(5-Data!H22)/4)*100,IF($Q22=$P22,50,IF(Data!$F22="higher",(J22-$P22)/($Q22-$P22),($Q22-J22)/($Q22-$P22))*100)) -> 25 | D22: =IF(Data!$E22="rubric",IF(Data!$F22="higher",(Data!I22-1)/4,(5-Data!I22)/4)*100,IF($Q22=$P22,50,IF(Data!$F22="higher",(K22-$P22)/($Q22-$P22),($Q22-K22)/($Q22-$P22))*100)) -> 0 | E22: =IF(Data!$E22="rubric",IF(Data!$F22="higher",(Data!J22-1)/4,(5-Data!J22)/4)*100,IF($Q22=$P22,50,IF(Data!$F22="higher",(L22-$P22)/($Q22-$P22),($Q22-L22)/($Q22-$P22))*100)) -> 75 | F22: =IF(Data!$E22="rubric",IF(Data!$F22="higher",(Data!K22-1)/4,(5-Data!K22)/4)*100,IF($Q22=$P22,50,IF(Data!$F22="higher",(M22-$P22)/($Q22-$P22),($Q22-M22)/($Q22-$P22))*100)) -> 25 | G22: =IF(Data!$E22="rubric",IF(Data!$F22="higher",(Data!L22-1)/4,(5-Data!L22)/4)*100,IF($Q22=$P22,50,IF(Data!$F22="higher",(N22-$P22)/($Q22-$P22),($Q22-N22)/($Q22-$P22))*100)) -> 100 | H22: =IF(Data!$E22="rubric",IF(Data!$F22="higher",(Data!M22-1)/4,(5-Data!M22)/4)*100,IF($Q22=$P22,50,IF(Data!$F22="higher",(O22-$P22)/($Q22-$P22),($Q22-O22)/($Q22-$P22))*100)) -> 50 | J22: =IF(Data!$G22="log",LN(Data!H22),Data!H22) -> 2 | K22: =IF(Data!$G22="log",LN(Data!I22),Data!I22) -> 1 | L22: =IF(Data!$G22="log",LN(Data!J22),Data!J22) -> 4 | M22: =IF(Data!$G22="log",LN(Data!K22),Data!K22) -> 2 | N22: =IF(Data!$G22="log",LN(Data!L22),Data!L22) -> 5 | O22: =IF(Data!$G22="log",LN(Data!M22),Data!M22) -> 3 | P22: =MIN(J22:O22) -> 1 | Q22: =MAX(J22:O22) -> 5
A24: Category scores (weighted by within-category shares)
A25: 1 | B25: =Weights!B5 -> Power & Grid | C25: =SUMPRODUCT(C5:C8,Weights!$D$16:$D$19)/SUM(Weights!$D$16:$D$19) -> 77.77439 | D25: =SUMPRODUCT(D5:D8,Weights!$D$16:$D$19)/SUM(Weights!$D$16:$D$19) -> 48.963415 | E25: =SUMPRODUCT(E5:E8,Weights!$D$16:$D$19)/SUM(Weights!$D$16:$D$19) -> 42.042683 | F25: =SUMPRODUCT(F5:F8,Weights!$D$16:$D$19)/SUM(Weights!$D$16:$D$19) -> 11.25 | G25: =SUMPRODUCT(G5:G8,Weights!$D$16:$D$19)/SUM(Weights!$D$16:$D$19) -> 81.25 | H25: =SUMPRODUCT(H5:H8,Weights!$D$16:$D$19)/SUM(Weights!$D$16:$D$19) -> 26.79878
A26: 2 | B26: =Weights!B6 -> Market & Pricing | C26: =SUMPRODUCT(C9:C12,Weights!$D$20:$D$23)/SUM(Weights!$D$20:$D$23) -> 80.018261 | D26: =SUMPRODUCT(D9:D12,Weights!$D$20:$D$23)/SUM(Weights!$D$20:$D$23) -> 7.0760761 | E26: =SUMPRODUCT(E9:E12,Weights!$D$20:$D$23)/SUM(Weights!$D$20:$D$23) -> 60.756569 | F26: =SUMPRODUCT(F9:F12,Weights!$D$20:$D$23)/SUM(Weights!$D$20:$D$23) -> 35.161405 | G26: =SUMPRODUCT(G9:G12,Weights!$D$20:$D$23)/SUM(Weights!$D$20:$D$23) -> 78.961612 | H26: =SUMPRODUCT(H9:H12,Weights!$D$20:$D$23)/SUM(Weights!$D$20:$D$23) -> 58.621192
A27: 3 | B27: =Weights!B7 -> Network & Latency | C27: =SUMPRODUCT(C13:C14,Weights!$D$24:$D$25)/SUM(Weights!$D$24:$D$25) -> 29.760629 | D27: =SUMPRODUCT(D13:D14,Weights!$D$24:$D$25)/SUM(Weights!$D$24:$D$25) -> 37.5 | E27: =SUMPRODUCT(E13:E14,Weights!$D$24:$D$25)/SUM(Weights!$D$24:$D$25) -> 48.964314 | F27: =SUMPRODUCT(F13:F14,Weights!$D$24:$D$25)/SUM(Weights!$D$24:$D$25) -> 97.467064 | G27: =SUMPRODUCT(G13:G14,Weights!$D$24:$D$25)/SUM(Weights!$D$24:$D$25) -> 82.148318 | H27: =SUMPRODUCT(H13:H14,Weights!$D$24:$D$25)/SUM(Weights!$D$24:$D$25) -> 75
A28: 4 | B28: =Weights!B8 -> Risk & Resilience | C28: =SUMPRODUCT(C15:C17,Weights!$D$26:$D$28)/SUM(Weights!$D$26:$D$28) -> 66.25 | D28: =SUMPRODUCT(D15:D17,Weights!$D$26:$D$28)/SUM(Weights!$D$26:$D$28) -> 40 | E28: =SUMPRODUCT(E15:E17,Weights!$D$26:$D$28)/SUM(Weights!$D$26:$D$28) -> 17.5 | F28: =SUMPRODUCT(F15:F17,Weights!$D$26:$D$28)/SUM(Weights!$D$26:$D$28) -> 50 | G28: =SUMPRODUCT(G15:G17,Weights!$D$26:$D$28)/SUM(Weights!$D$26:$D$28) -> 32.5 | H28: =SUMPRODUCT(H15:H17,Weights!$D$26:$D$28)/SUM(Weights!$D$26:$D$28) -> 73.75
A29: 5 | B29: =Weights!B9 -> Policy & Incentives | C29: =SUMPRODUCT(C18:C18,Weights!$D$29:$D$29)/SUM(Weights!$D$29:$D$29) -> 50 | D29: =SUMPRODUCT(D18:D18,Weights!$D$29:$D$29)/SUM(Weights!$D$29:$D$29) -> 0 | E29: =SUMPRODUCT(E18:E18,Weights!$D$29:$D$29)/SUM(Weights!$D$29:$D$29) -> 0 | F29: =SUMPRODUCT(F18:F18,Weights!$D$29:$D$29)/SUM(Weights!$D$29:$D$29) -> 75 | G29: =SUMPRODUCT(G18:G18,Weights!$D$29:$D$29)/SUM(Weights!$D$29:$D$29) -> 75 | H29: =SUMPRODUCT(H18:H18,Weights!$D$29:$D$29)/SUM(Weights!$D$29:$D$29) -> 0
A30: 6 | B30: =Weights!B10 -> Build & Operations | C30: =SUMPRODUCT(C19:C20,Weights!$D$30:$D$31)/SUM(Weights!$D$30:$D$31) -> 50 | D30: =SUMPRODUCT(D19:D20,Weights!$D$30:$D$31)/SUM(Weights!$D$30:$D$31) -> 62.5 | E30: =SUMPRODUCT(E19:E20,Weights!$D$30:$D$31)/SUM(Weights!$D$30:$D$31) -> 37.5 | F30: =SUMPRODUCT(F19:F20,Weights!$D$30:$D$31)/SUM(Weights!$D$30:$D$31) -> 50 | G30: =SUMPRODUCT(G19:G20,Weights!$D$30:$D$31)/SUM(Weights!$D$30:$D$31) -> 62.5 | H30: =SUMPRODUCT(H19:H20,Weights!$D$30:$D$31)/SUM(Weights!$D$30:$D$31) -> 50
A31: 7 | B31: =Weights!B11 -> Growth Headroom | C31: =SUMPRODUCT(C21:C22,Weights!$D$32:$D$33)/SUM(Weights!$D$32:$D$33) -> 25 | D31: =SUMPRODUCT(D21:D22,Weights!$D$32:$D$33)/SUM(Weights!$D$32:$D$33) -> 0 | E31: =SUMPRODUCT(E21:E22,Weights!$D$32:$D$33)/SUM(Weights!$D$32:$D$33) -> 60 | F31: =SUMPRODUCT(F21:F22,Weights!$D$32:$D$33)/SUM(Weights!$D$32:$D$33) -> 25 | G31: =SUMPRODUCT(G21:G22,Weights!$D$32:$D$33)/SUM(Weights!$D$32:$D$33) -> 85 | H31: =SUMPRODUCT(H21:H22,Weights!$D$32:$D$33)/SUM(Weights!$D$32:$D$33) -> 50
B33: TOTAL weighted score (selected scenario) | C33: =SUMPRODUCT(Weights!$J$5:$J$11,C25:C31) -> 61.844745 | D33: =SUMPRODUCT(Weights!$J$5:$J$11,D25:D31) -> 29.72924 | E33: =SUMPRODUCT(Weights!$J$5:$J$11,E25:E31) -> 41.139836 | F33: =SUMPRODUCT(Weights!$J$5:$J$11,F25:F31) -> 40.603329 | G33: =SUMPRODUCT(Weights!$J$5:$J$11,G25:G31) -> 72.525121 | H33: =SUMPRODUCT(Weights!$J$5:$J$11,H25:H31) -> 47.326373
B34: Rank (1 = best) | C34: =RANK(C33,$C$33:$H$33) -> 2 | D34: =RANK(D33,$C$33:$H$33) -> 6 | E34: =RANK(E33,$C$33:$H$33) -> 4 | F34: =RANK(F33,$C$33:$H$33) -> 5 | G34: =RANK(G33,$C$33:$H$33) -> 1 | H34: =RANK(H33,$C$33:$H$33) -> 3
B35: Check: total via variable weights minus total via category weights (should be 0) | C35: =ROUND(SUMPRODUCT(C5:C22,Weights!$L$16:$L$33)-C33,6) -> 0 | D35: =ROUND(SUMPRODUCT(D5:D22,Weights!$L$16:$L$33)-D33,6) -> 0 | E35: =ROUND(SUMPRODUCT(E5:E22,Weights!$L$16:$L$33)-E33,6) -> 0 | F35: =ROUND(SUMPRODUCT(F5:F22,Weights!$L$16:$L$33)-F33,6) -> 0 | G35: =ROUND(SUMPRODUCT(G5:G22,Weights!$L$16:$L$33)-G33,6) -> 0 | H35: =ROUND(SUMPRODUCT(H5:H22,Weights!$L$16:$L$33)-H33,6) -> 0

Sheet Sensitivity
A1: Sensitivity - how the ranking moves with the weights
A2: All cells are formulas driven by the Scoring and Weights sheets. 'Custom' reflects whatever you type into the Custom column on Weights.
A3: 1. Weighted score (0-100) by scenario
A4: Market | B4: Base | C4: Power-first | D4: Latency-first | E4: Cost-first | F4: Risk/Regulatory-first | G4: Speed-to-market | H4: Custom
A5: Seattle / Quincy, WA | B5: =SUMPRODUCT(Weights!C$5:C$11,Scoring!C$25:C$31) -> 61.844745 | C5: =SUMPRODUCT(Weights!D$5:D$11,Scoring!C$25:C$31) -> 64.832065 | D5: =SUMPRODUCT(Weights!E$5:E$11,Scoring!C$25:C$31) -> 52.935806 | E5: =SUMPRODUCT(Weights!F$5:F$11,Scoring!C$25:C$31) -> 63.954926 | F5: =SUMPRODUCT(Weights!G$5:G$11,Scoring!C$25:C$31) -> 60.643408 | G5: =SUMPRODUCT(Weights!H$5:H$11,Scoring!C$25:C$31) -> 63.501665 | H5: =SUMPRODUCT(Weights!I$5:I$11,Scoring!C$25:C$31) -> 61.844745
A6: Hillsboro / Portland, OR | B6: =SUMPRODUCT(Weights!C$5:C$11,Scoring!D$25:D$31) -> 29.72924 | C6: =SUMPRODUCT(Weights!D$5:D$11,Scoring!D$25:D$31) -> 33.394948 | D6: =SUMPRODUCT(Weights!E$5:E$11,Scoring!D$25:D$31) -> 30.029094 | E6: =SUMPRODUCT(Weights!F$5:F$11,Scoring!D$25:D$31) -> 23.863676 | F6: =SUMPRODUCT(Weights!G$5:G$11,Scoring!D$25:D$31) -> 28.32108 | G6: =SUMPRODUCT(Weights!H$5:H$11,Scoring!D$25:D$31) -> 28.356214 | H6: =SUMPRODUCT(Weights!I$5:I$11,Scoring!D$25:D$31) -> 29.72924
A7: Phoenix, AZ | B7: =SUMPRODUCT(Weights!C$5:C$11,Scoring!E$25:E$31) -> 41.139836 | C7: =SUMPRODUCT(Weights!D$5:D$11,Scoring!E$25:E$31) -> 41.549838 | D7: =SUMPRODUCT(Weights!E$5:E$11,Scoring!E$25:E$31) -> 43.386316 | E7: =SUMPRODUCT(Weights!F$5:F$11,Scoring!E$25:E$31) -> 40.704787 | F7: =SUMPRODUCT(Weights!G$5:G$11,Scoring!E$25:E$31) -> 31.657324 | G7: =SUMPRODUCT(Weights!H$5:H$11,Scoring!E$25:E$31) -> 44.900513 | H7: =SUMPRODUCT(Weights!I$5:I$11,Scoring!E$25:E$31) -> 41.139836
A8: Northern Virginia | B8: =SUMPRODUCT(Weights!C$5:C$11,Scoring!F$25:F$31) -> 40.603329 | C8: =SUMPRODUCT(Weights!D$5:D$11,Scoring!F$25:F$31) -> 33.134076 | D8: =SUMPRODUCT(Weights!E$5:E$11,Scoring!F$25:F$31) -> 52.76433 | E8: =SUMPRODUCT(Weights!F$5:F$11,Scoring!F$25:F$31) -> 41.408287 | F8: =SUMPRODUCT(Weights!G$5:G$11,Scoring!F$25:F$31) -> 45.991734 | G8: =SUMPRODUCT(Weights!H$5:H$11,Scoring!F$25:F$31) -> 35.974558 | H8: =SUMPRODUCT(Weights!I$5:I$11,Scoring!F$25:F$31) -> 40.603329
A9: Dallas-Fort Worth, TX | B9: =SUMPRODUCT(Weights!C$5:C$11,Scoring!G$25:G$31) -> 72.525121 | C9: =SUMPRODUCT(Weights!D$5:D$11,Scoring!G$25:G$31) -> 74.378607 | D9: =SUMPRODUCT(Weights!E$5:E$11,Scoring!G$25:G$31) -> 74.463737 | E9: =SUMPRODUCT(Weights!F$5:F$11,Scoring!G$25:G$31) -> 74.372849 | F9: =SUMPRODUCT(Weights!G$5:G$11,Scoring!G$25:G$31) -> 65.822259 | G9: =SUMPRODUCT(Weights!H$5:H$11,Scoring!G$25:G$31) -> 76.192735 | H9: =SUMPRODUCT(Weights!I$5:I$11,Scoring!G$25:G$31) -> 72.525121
A10: Columbus, OH | B10: =SUMPRODUCT(Weights!C$5:C$11,Scoring!H$25:H$31) -> 47.326373 | C10: =SUMPRODUCT(Weights!D$5:D$11,Scoring!H$25:H$31) -> 42.70263 | D10: =SUMPRODUCT(Weights!E$5:E$11,Scoring!H$25:H$31) -> 54.002935 | E10: =SUMPRODUCT(Weights!F$5:F$11,Scoring!H$25:H$31) -> 43.661053 | F10: =SUMPRODUCT(Weights!G$5:G$11,Scoring!H$25:H$31) -> 45.580275 | G10: =SUMPRODUCT(Weights!H$5:H$11,Scoring!H$25:H$31) -> 45.434871 | H10: =SUMPRODUCT(Weights!I$5:I$11,Scoring!H$25:H$31) -> 47.326373
A12: 2. Rank by scenario (1 = best)
A13: Market | B13: Base | C13: Power-first | D13: Latency-first | E13: Cost-first | F13: Risk/Regulatory-first | G13: Speed-to-market | H13: Custom | J13: Best rank | K13: Worst rank | L13: Avg rank | M13: # first places
A14: Seattle / Quincy, WA | B14: =RANK(B5,B$5:B$10) -> 2 | C14: =RANK(C5,C$5:C$10) -> 2 | D14: =RANK(D5,D$5:D$10) -> 3 | E14: =RANK(E5,E$5:E$10) -> 2 | F14: =RANK(F5,F$5:F$10) -> 2 | G14: =RANK(G5,G$5:G$10) -> 2 | H14: =RANK(H5,H$5:H$10) -> 2 | J14: =MIN(B14:G14) -> 2 | K14: =MAX(B14:G14) -> 3 | L14: =AVERAGE(B14:G14) -> 2.1666667 | M14: =COUNTIF(B14:G14,1) -> 0
A15: Hillsboro / Portland, OR | B15: =RANK(B6,B$5:B$10) -> 6 | C15: =RANK(C6,C$5:C$10) -> 5 | D15: =RANK(D6,D$5:D$10) -> 6 | E15: =RANK(E6,E$5:E$10) -> 6 | F15: =RANK(F6,F$5:F$10) -> 6 | G15: =RANK(G6,G$5:G$10) -> 6 | H15: =RANK(H6,H$5:H$10) -> 6 | J15: =MIN(B15:G15) -> 5 | K15: =MAX(B15:G15) -> 6 | L15: =AVERAGE(B15:G15) -> 5.8333333 | M15: =COUNTIF(B15:G15,1) -> 0
A16: Phoenix, AZ | B16: =RANK(B7,B$5:B$10) -> 4 | C16: =RANK(C7,C$5:C$10) -> 4 | D16: =RANK(D7,D$5:D$10) -> 5 | E16: =RANK(E7,E$5:E$10) -> 5 | F16: =RANK(F7,F$5:F$10) -> 5 | G16: =RANK(G7,G$5:G$10) -> 4 | H16: =RANK(H7,H$5:H$10) -> 4 | J16: =MIN(B16:G16) -> 4 | K16: =MAX(B16:G16) -> 5 | L16: =AVERAGE(B16:G16) -> 4.5 | M16: =COUNTIF(B16:G16,1) -> 0
A17: Northern Virginia | B17: =RANK(B8,B$5:B$10) -> 5 | C17: =RANK(C8,C$5:C$10) -> 6 | D17: =RANK(D8,D$5:D$10) -> 4 | E17: =RANK(E8,E$5:E$10) -> 4 | F17: =RANK(F8,F$5:F$10) -> 3 | G17: =RANK(G8,G$5:G$10) -> 5 | H17: =RANK(H8,H$5:H$10) -> 5 | J17: =MIN(B17:G17) -> 3 | K17: =MAX(B17:G17) -> 6 | L17: =AVERAGE(B17:G17) -> 4.5 | M17: =COUNTIF(B17:G17,1) -> 0
A18: Dallas-Fort Worth, TX | B18: =RANK(B9,B$5:B$10) -> 1 | C18: =RANK(C9,C$5:C$10) -> 1 | D18: =RANK(D9,D$5:D$10) -> 1 | E18: =RANK(E9,E$5:E$10) -> 1 | F18: =RANK(F9,F$5:F$10) -> 1 | G18: =RANK(G9,G$5:G$10) -> 1 | H18: =RANK(H9,H$5:H$10) -> 1 | J18: =MIN(B18:G18) -> 1 | K18: =MAX(B18:G18) -> 1 | L18: =AVERAGE(B18:G18) -> 1 | M18: =COUNTIF(B18:G18,1) -> 6
A19: Columbus, OH | B19: =RANK(B10,B$5:B$10) -> 3 | C19: =RANK(C10,C$5:C$10) -> 3 | D19: =RANK(D10,D$5:D$10) -> 2 | E19: =RANK(E10,E$5:E$10) -> 3 | F19: =RANK(F10,F$5:F$10) -> 4 | G19: =RANK(G10,G$5:G$10) -> 3 | H19: =RANK(H10,H$5:H$10) -> 3 | J19: =MIN(B19:G19) -> 2 | K19: =MAX(B19:G19) -> 4 | L19: =AVERAGE(B19:G19) -> 3 | M19: =COUNTIF(B19:G19,1) -> 0
J20: Best/worst/avg/# first places use the six named scenarios (columns B-G), excluding Custom.
A22: 3. One-way sweep: weight on Power & Grid (other categories scaled proportionally from Base)
A23: Power weight | B23: Seattle / Quincy, WA | C23: Hillsboro / Portland, OR | D23: Phoenix, AZ | E23: Northern Virginia | F23: Dallas-Fort Worth, TX | G23: Columbus, OH | H23: Leader
A24: 0.1 | B24: =$A24*Scoring!C$25+(1-$A24)/(1-Weights!$C$5)*($B$5-Weights!$C$5*Scoring!C$25) -> 57.293418 | C24: =$A24*Scoring!D$25+(1-$A24)/(1-Weights!$C$5)*($B$6-Weights!$C$5*Scoring!D$25) -> 24.233761 | D24: =$A24*Scoring!E$25+(1-$A24)/(1-Weights!$C$5)*($B$7-Weights!$C$5*Scoring!E$25) -> 40.88188 | E24: =$A24*Scoring!F$25+(1-$A24)/(1-Weights!$C$5)*($B$8-Weights!$C$5*Scoring!F$25) -> 48.989994 | F24: =$A24*Scoring!G$25+(1-$A24)/(1-Weights!$C$5)*($B$9-Weights!$C$5*Scoring!G$25) -> 70.032298 | G24: =$A24*Scoring!H$25+(1-$A24)/(1-Weights!$C$5)*($B$10-Weights!$C$5*Scoring!H$25) -> 53.191399 | H24: =INDEX($B$23:$G$23,MATCH(MAX(B24:G24),B24:G24,0)) -> Dallas-Fort Worth, TX
A25: 0.15 | B25: =$A25*Scoring!C$25+(1-$A25)/(1-Weights!$C$5)*($B$5-Weights!$C$5*Scoring!C$25) -> 58.431249 | C25: =$A25*Scoring!D$25+(1-$A25)/(1-Weights!$C$5)*($B$6-Weights!$C$5*Scoring!D$25) -> 25.607631 | D25: =$A25*Scoring!E$25+(1-$A25)/(1-Weights!$C$5)*($B$7-Weights!$C$5*Scoring!E$25) -> 40.946369 | E25: =$A25*Scoring!F$25+(1-$A25)/(1-Weights!$C$5)*($B$8-Weights!$C$5*Scoring!F$25) -> 46.893328 | F25: =$A25*Scoring!G$25+(1-$A25)/(1-Weights!$C$5)*($B$9-Weights!$C$5*Scoring!G$25) -> 70.655504 | G25: =$A25*Scoring!H$25+(1-$A25)/(1-Weights!$C$5)*($B$10-Weights!$C$5*Scoring!H$25) -> 51.725142 | H25: =INDEX($B$23:$G$23,MATCH(MAX(B25:G25),B25:G25,0)) -> Dallas-Fort Worth, TX
A26: 0.2 | B26: =$A26*Scoring!C$25+(1-$A26)/(1-Weights!$C$5)*($B$5-Weights!$C$5*Scoring!C$25) -> 59.569081 | C26: =$A26*Scoring!D$25+(1-$A26)/(1-Weights!$C$5)*($B$6-Weights!$C$5*Scoring!D$25) -> 26.9815 | D26: =$A26*Scoring!E$25+(1-$A26)/(1-Weights!$C$5)*($B$7-Weights!$C$5*Scoring!E$25) -> 41.010858 | E26: =$A26*Scoring!F$25+(1-$A26)/(1-Weights!$C$5)*($B$8-Weights!$C$5*Scoring!F$25) -> 44.796661 | F26: =$A26*Scoring!G$25+(1-$A26)/(1-Weights!$C$5)*($B$9-Weights!$C$5*Scoring!G$25) -> 71.278709 | G26: =$A26*Scoring!H$25+(1-$A26)/(1-Weights!$C$5)*($B$10-Weights!$C$5*Scoring!H$25) -> 50.258886 | H26: =INDEX($B$23:$G$23,MATCH(MAX(B26:G26),B26:G26,0)) -> Dallas-Fort Worth, TX
A27: 0.25 | B27: =$A27*Scoring!C$25+(1-$A27)/(1-Weights!$C$5)*($B$5-Weights!$C$5*Scoring!C$25) -> 60.706913 | C27: =$A27*Scoring!D$25+(1-$A27)/(1-Weights!$C$5)*($B$6-Weights!$C$5*Scoring!D$25) -> 28.35537 | D27: =$A27*Scoring!E$25+(1-$A27)/(1-Weights!$C$5)*($B$7-Weights!$C$5*Scoring!E$25) -> 41.075347 | E27: =$A27*Scoring!F$25+(1-$A27)/(1-Weights!$C$5)*($B$8-Weights!$C$5*Scoring!F$25) -> 42.699995 | F27: =$A27*Scoring!G$25+(1-$A27)/(1-Weights!$C$5)*($B$9-Weights!$C$5*Scoring!G$25) -> 71.901915 | G27: =$A27*Scoring!H$25+(1-$A27)/(1-Weights!$C$5)*($B$10-Weights!$C$5*Scoring!H$25) -> 48.792629 | H27: =INDEX($B$23:$G$23,MATCH(MAX(B27:G27),B27:G27,0)) -> Dallas-Fort Worth, TX
A28: 0.3 | B28: =$A28*Scoring!C$25+(1-$A28)/(1-Weights!$C$5)*($B$5-Weights!$C$5*Scoring!C$25) -> 61.844745 | C28: =$A28*Scoring!D$25+(1-$A28)/(1-Weights!$C$5)*($B$6-Weights!$C$5*Scoring!D$25) -> 29.72924 | D28: =$A28*Scoring!E$25+(1-$A28)/(1-Weights!$C$5)*($B$7-Weights!$C$5*Scoring!E$25) -> 41.139836 | E28: =$A28*Scoring!F$25+(1-$A28)/(1-Weights!$C$5)*($B$8-Weights!$C$5*Scoring!F$25) -> 40.603329 | F28: =$A28*Scoring!G$25+(1-$A28)/(1-Weights!$C$5)*($B$9-Weights!$C$5*Scoring!G$25) -> 72.525121 | G28: =$A28*Scoring!H$25+(1-$A28)/(1-Weights!$C$5)*($B$10-Weights!$C$5*Scoring!H$25) -> 47.326373 | H28: =INDEX($B$23:$G$23,MATCH(MAX(B28:G28),B28:G28,0)) -> Dallas-Fort Worth, TX
A29: 0.35 | B29: =$A29*Scoring!C$25+(1-$A29)/(1-Weights!$C$5)*($B$5-Weights!$C$5*Scoring!C$25) -> 62.982577 | C29: =$A29*Scoring!D$25+(1-$A29)/(1-Weights!$C$5)*($B$6-Weights!$C$5*Scoring!D$25) -> 31.103109 | D29: =$A29*Scoring!E$25+(1-$A29)/(1-Weights!$C$5)*($B$7-Weights!$C$5*Scoring!E$25) -> 41.204325 | E29: =$A29*Scoring!F$25+(1-$A29)/(1-Weights!$C$5)*($B$8-Weights!$C$5*Scoring!F$25) -> 38.506662 | F29: =$A29*Scoring!G$25+(1-$A29)/(1-Weights!$C$5)*($B$9-Weights!$C$5*Scoring!G$25) -> 73.148326 | G29: =$A29*Scoring!H$25+(1-$A29)/(1-Weights!$C$5)*($B$10-Weights!$C$5*Scoring!H$25) -> 45.860116 | H29: =INDEX($B$23:$G$23,MATCH(MAX(B29:G29),B29:G29,0)) -> Dallas-Fort Worth, TX
A30: 0.4 | B30: =$A30*Scoring!C$25+(1-$A30)/(1-Weights!$C$5)*($B$5-Weights!$C$5*Scoring!C$25) -> 64.120408 | C30: =$A30*Scoring!D$25+(1-$A30)/(1-Weights!$C$5)*($B$6-Weights!$C$5*Scoring!D$25) -> 32.476979 | D30: =$A30*Scoring!E$25+(1-$A30)/(1-Weights!$C$5)*($B$7-Weights!$C$5*Scoring!E$25) -> 41.268814 | E30: =$A30*Scoring!F$25+(1-$A30)/(1-Weights!$C$5)*($B$8-Weights!$C$5*Scoring!F$25) -> 36.409996 | F30: =$A30*Scoring!G$25+(1-$A30)/(1-Weights!$C$5)*($B$9-Weights!$C$5*Scoring!G$25) -> 73.771532 | G30: =$A30*Scoring!H$25+(1-$A30)/(1-Weights!$C$5)*($B$10-Weights!$C$5*Scoring!H$25) -> 44.393859 | H30: =INDEX($B$23:$G$23,MATCH(MAX(B30:G30),B30:G30,0)) -> Dallas-Fort Worth, TX
A31: 0.45 | B31: =$A31*Scoring!C$25+(1-$A31)/(1-Weights!$C$5)*($B$5-Weights!$C$5*Scoring!C$25) -> 65.25824 | C31: =$A31*Scoring!D$25+(1-$A31)/(1-Weights!$C$5)*($B$6-Weights!$C$5*Scoring!D$25) -> 33.850849 | D31: =$A31*Scoring!E$25+(1-$A31)/(1-Weights!$C$5)*($B$7-Weights!$C$5*Scoring!E$25) -> 41.333303 | E31: =$A31*Scoring!F$25+(1-$A31)/(1-Weights!$C$5)*($B$8-Weights!$C$5*Scoring!F$25) -> 34.31333 | F31: =$A31*Scoring!G$25+(1-$A31)/(1-Weights!$C$5)*($B$9-Weights!$C$5*Scoring!G$25) -> 74.394738 | G31: =$A31*Scoring!H$25+(1-$A31)/(1-Weights!$C$5)*($B$10-Weights!$C$5*Scoring!H$25) -> 42.927603 | H31: =INDEX($B$23:$G$23,MATCH(MAX(B31:G31),B31:G31,0)) -> Dallas-Fort Worth, TX
A32: 0.5 | B32: =$A32*Scoring!C$25+(1-$A32)/(1-Weights!$C$5)*($B$5-Weights!$C$5*Scoring!C$25) -> 66.396072 | C32: =$A32*Scoring!D$25+(1-$A32)/(1-Weights!$C$5)*($B$6-Weights!$C$5*Scoring!D$25) -> 35.224718 | D32: =$A32*Scoring!E$25+(1-$A32)/(1-Weights!$C$5)*($B$7-Weights!$C$5*Scoring!E$25) -> 41.397792 | E32: =$A32*Scoring!F$25+(1-$A32)/(1-Weights!$C$5)*($B$8-Weights!$C$5*Scoring!F$25) -> 32.216663 | F32: =$A32*Scoring!G$25+(1-$A32)/(1-Weights!$C$5)*($B$9-Weights!$C$5*Scoring!G$25) -> 75.017943 | G32: =$A32*Scoring!H$25+(1-$A32)/(1-Weights!$C$5)*($B$10-Weights!$C$5*Scoring!H$25) -> 41.461346 | H32: =INDEX($B$23:$G$23,MATCH(MAX(B32:G32),B32:G32,0)) -> Dallas-Fort Worth, TX
A33: 0.55 | B33: =$A33*Scoring!C$25+(1-$A33)/(1-Weights!$C$5)*($B$5-Weights!$C$5*Scoring!C$25) -> 67.533904 | C33: =$A33*Scoring!D$25+(1-$A33)/(1-Weights!$C$5)*($B$6-Weights!$C$5*Scoring!D$25) -> 36.598588 | D33: =$A33*Scoring!E$25+(1-$A33)/(1-Weights!$C$5)*($B$7-Weights!$C$5*Scoring!E$25) -> 41.462282 | E33: =$A33*Scoring!F$25+(1-$A33)/(1-Weights!$C$5)*($B$8-Weights!$C$5*Scoring!F$25) -> 30.119997 | F33: =$A33*Scoring!G$25+(1-$A33)/(1-Weights!$C$5)*($B$9-Weights!$C$5*Scoring!G$25) -> 75.641149 | G33: =$A33*Scoring!H$25+(1-$A33)/(1-Weights!$C$5)*($B$10-Weights!$C$5*Scoring!H$25) -> 39.99509 | H33: =INDEX($B$23:$G$23,MATCH(MAX(B33:G33),B33:G33,0)) -> Dallas-Fort Worth, TX
A34: 0.6 | B34: =$A34*Scoring!C$25+(1-$A34)/(1-Weights!$C$5)*($B$5-Weights!$C$5*Scoring!C$25) -> 68.671736 | C34: =$A34*Scoring!D$25+(1-$A34)/(1-Weights!$C$5)*($B$6-Weights!$C$5*Scoring!D$25) -> 37.972457 | D34: =$A34*Scoring!E$25+(1-$A34)/(1-Weights!$C$5)*($B$7-Weights!$C$5*Scoring!E$25) -> 41.526771 | E34: =$A34*Scoring!F$25+(1-$A34)/(1-Weights!$C$5)*($B$8-Weights!$C$5*Scoring!F$25) -> 28.023331 | F34: =$A34*Scoring!G$25+(1-$A34)/(1-Weights!$C$5)*($B$9-Weights!$C$5*Scoring!G$25) -> 76.264355 | G34: =$A34*Scoring!H$25+(1-$A34)/(1-Weights!$C$5)*($B$10-Weights!$C$5*Scoring!H$25) -> 38.528833 | H34: =INDEX($B$23:$G$23,MATCH(MAX(B34:G34),B34:G34,0)) -> Dallas-Fort Worth, TX
A37: 4. Two-way sweep: Power weight vs Network & Latency weight (other categories scaled proportionally from Base). Cell = leading market.
A38: Power wt | B38: Latency wt | C38: Seattle / Quincy, WA | D38: Hillsboro / Portland, OR | E38: Phoenix, AZ | F38: Northern Virginia | G38: Dallas-Fort Worth, TX | H38: Columbus, OH | I38: Leader
A39: 0.15 | B39: 0.05 | C39: =$A39*Scoring!C$25+$B39*Scoring!C$27+((1-$A39-$B39)/(1-Weights!$C$5-Weights!$C$7))*($B$5-Weights!$C$5*Scoring!C$25-Weights!$C$7*Scoring!C$27) -> 61.348883 | D39: =$A39*Scoring!D$25+$B39*Scoring!D$27+((1-$A39-$B39)/(1-Weights!$C$5-Weights!$C$7))*($B$6-Weights!$C$5*Scoring!D$25-Weights!$C$7*Scoring!D$27) -> 23.75774 | E39: =$A39*Scoring!E$25+$B39*Scoring!E$27+((1-$A39-$B39)/(1-Weights!$C$5-Weights!$C$7))*($B$7-Weights!$C$5*Scoring!E$25-Weights!$C$7*Scoring!E$27) -> 39.99781 | F39: =$A39*Scoring!F$25+$B39*Scoring!F$27+((1-$A39-$B39)/(1-Weights!$C$5-Weights!$C$7))*($B$8-Weights!$C$5*Scoring!F$25-Weights!$C$7*Scoring!F$27) -> 41.777792 | G39: =$A39*Scoring!G$25+$B39*Scoring!G$27+((1-$A39-$B39)/(1-Weights!$C$5-Weights!$C$7))*($B$9-Weights!$C$5*Scoring!G$25-Weights!$C$7*Scoring!G$27) -> 69.111912 | H39: =$A39*Scoring!H$25+$B39*Scoring!H$27+((1-$A39-$B39)/(1-Weights!$C$5-Weights!$C$7))*($B$10-Weights!$C$5*Scoring!H$25-Weights!$C$7*Scoring!H$27) -> 49.544629 | I39: =INDEX($C$38:$H$38,MATCH(MAX(C39:H39),C39:H39,0)) -> Dallas-Fort Worth, TX
A40: 0.15 | B40: 0.1 | C40: =$A40*Scoring!C$25+$B40*Scoring!C$27+((1-$A40-$B40)/(1-Weights!$C$5-Weights!$C$7))*($B$5-Weights!$C$5*Scoring!C$25-Weights!$C$7*Scoring!C$27) -> 59.824746 | D40: =$A40*Scoring!D$25+$B40*Scoring!D$27+((1-$A40-$B40)/(1-Weights!$C$5-Weights!$C$7))*($B$6-Weights!$C$5*Scoring!D$25-Weights!$C$7*Scoring!D$27) -> 24.724101 | E40: =$A40*Scoring!E$25+$B40*Scoring!E$27+((1-$A40-$B40)/(1-Weights!$C$5-Weights!$C$7))*($B$7-Weights!$C$5*Scoring!E$25-Weights!$C$7*Scoring!E$27) -> 40.493326 | F40: =$A40*Scoring!F$25+$B40*Scoring!F$27+((1-$A40-$B40)/(1-Weights!$C$5-Weights!$C$7))*($B$8-Weights!$C$5*Scoring!F$25-Weights!$C$7*Scoring!F$27) -> 44.450087 | G40: =$A40*Scoring!G$25+$B40*Scoring!G$27+((1-$A40-$B40)/(1-Weights!$C$5-Weights!$C$7))*($B$9-Weights!$C$5*Scoring!G$25-Weights!$C$7*Scoring!G$27) -> 69.918266 | H40: =$A40*Scoring!H$25+$B40*Scoring!H$27+((1-$A40-$B40)/(1-Weights!$C$5-Weights!$C$7))*($B$10-Weights!$C$5*Scoring!H$25-Weights!$C$7*Scoring!H$27) -> 50.683703 | I40: =INDEX($C$38:$H$38,MATCH(MAX(C40:H40),C40:H40,0)) -> Dallas-Fort Worth, TX
A41: 0.15 | B41: 0.2 | C41: =$A41*Scoring!C$25+$B41*Scoring!C$27+((1-$A41-$B41)/(1-Weights!$C$5-Weights!$C$7))*($B$5-Weights!$C$5*Scoring!C$25-Weights!$C$7*Scoring!C$27) -> 56.776472 | D41: =$A41*Scoring!D$25+$B41*Scoring!D$27+((1-$A41-$B41)/(1-Weights!$C$5-Weights!$C$7))*($B$6-Weights!$C$5*Scoring!D$25-Weights!$C$7*Scoring!D$27) -> 26.656822 | E41: =$A41*Scoring!E$25+$B41*Scoring!E$27+((1-$A41-$B41)/(1-Weights!$C$5-Weights!$C$7))*($B$7-Weights!$C$5*Scoring!E$25-Weights!$C$7*Scoring!E$27) -> 41.484358 | F41: =$A41*Scoring!F$25+$B41*Scoring!F$27+((1-$A41-$B41)/(1-Weights!$C$5-Weights!$C$7))*($B$8-Weights!$C$5*Scoring!F$25-Weights!$C$7*Scoring!F$27) -> 49.794676 | G41: =$A41*Scoring!G$25+$B41*Scoring!G$27+((1-$A41-$B41)/(1-Weights!$C$5-Weights!$C$7))*($B$9-Weights!$C$5*Scoring!G$25-Weights!$C$7*Scoring!G$27) -> 71.530973 | H41: =$A41*Scoring!H$25+$B41*Scoring!H$27+((1-$A41-$B41)/(1-Weights!$C$5-Weights!$C$7))*($B$10-Weights!$C$5*Scoring!H$25-Weights!$C$7*Scoring!H$27) -> 52.961852 | I41: =INDEX($C$38:$H$38,MATCH(MAX(C41:H41),C41:H41,0)) -> Dallas-Fort Worth, TX
A42: 0.15 | B42: 0.3 | C42: =$A42*Scoring!C$25+$B42*Scoring!C$27+((1-$A42-$B42)/(1-Weights!$C$5-Weights!$C$7))*($B$5-Weights!$C$5*Scoring!C$25-Weights!$C$7*Scoring!C$27) -> 53.728198 | D42: =$A42*Scoring!D$25+$B42*Scoring!D$27+((1-$A42-$B42)/(1-Weights!$C$5-Weights!$C$7))*($B$6-Weights!$C$5*Scoring!D$25-Weights!$C$7*Scoring!D$27) -> 28.589544 | E42: =$A42*Scoring!E$25+$B42*Scoring!E$27+((1-$A42-$B42)/(1-Weights!$C$5-Weights!$C$7))*($B$7-Weights!$C$5*Scoring!E$25-Weights!$C$7*Scoring!E$27) -> 42.475391 | F42: =$A42*Scoring!F$25+$B42*Scoring!F$27+((1-$A42-$B42)/(1-Weights!$C$5-Weights!$C$7))*($B$8-Weights!$C$5*Scoring!F$25-Weights!$C$7*Scoring!F$27) -> 55.139265 | G42: =$A42*Scoring!G$25+$B42*Scoring!G$27+((1-$A42-$B42)/(1-Weights!$C$5-Weights!$C$7))*($B$9-Weights!$C$5*Scoring!G$25-Weights!$C$7*Scoring!G$27) -> 73.14368 | H42: =$A42*Scoring!H$25+$B42*Scoring!H$27+((1-$A42-$B42)/(1-Weights!$C$5-Weights!$C$7))*($B$10-Weights!$C$5*Scoring!H$25-Weights!$C$7*Scoring!H$27) -> 55.24 | I42: =INDEX($C$38:$H$38,MATCH(MAX(C42:H42),C42:H42,0)) -> Dallas-Fort Worth, TX
A43: 0.25 | B43: 0.05 | C43: =$A43*Scoring!C$25+$B43*Scoring!C$27+((1-$A43-$B43)/(1-Weights!$C$5-Weights!$C$7))*($B$5-Weights!$C$5*Scoring!C$25-Weights!$C$7*Scoring!C$27) -> 63.101985 | D43: =$A43*Scoring!D$25+$B43*Scoring!D$27+((1-$A43-$B43)/(1-Weights!$C$5-Weights!$C$7))*($B$6-Weights!$C$5*Scoring!D$25-Weights!$C$7*Scoring!D$27) -> 26.836803 | E43: =$A43*Scoring!E$25+$B43*Scoring!E$27+((1-$A43-$B43)/(1-Weights!$C$5-Weights!$C$7))*($B$7-Weights!$C$5*Scoring!E$25-Weights!$C$7*Scoring!E$27) -> 40.296679 | F43: =$A43*Scoring!F$25+$B43*Scoring!F$27+((1-$A43-$B43)/(1-Weights!$C$5-Weights!$C$7))*($B$8-Weights!$C$5*Scoring!F$25-Weights!$C$7*Scoring!F$27) -> 38.500675 | G43: =$A43*Scoring!G$25+$B43*Scoring!G$27+((1-$A43-$B43)/(1-Weights!$C$5-Weights!$C$7))*($B$9-Weights!$C$5*Scoring!G$25-Weights!$C$7*Scoring!G$27) -> 70.634788 | H43: =$A43*Scoring!H$25+$B43*Scoring!H$27+((1-$A43-$B43)/(1-Weights!$C$5-Weights!$C$7))*($B$10-Weights!$C$5*Scoring!H$25-Weights!$C$7*Scoring!H$27) -> 47.002655 | I43: =INDEX($C$38:$H$38,MATCH(MAX(C43:H43),C43:H43,0)) -> Dallas-Fort Worth, TX
A44: 0.25 | B44: 0.1 | C44: =$A44*Scoring!C$25+$B44*Scoring!C$27+((1-$A44-$B44)/(1-Weights!$C$5-Weights!$C$7))*($B$5-Weights!$C$5*Scoring!C$25-Weights!$C$7*Scoring!C$27) -> 61.577848 | D44: =$A44*Scoring!D$25+$B44*Scoring!D$27+((1-$A44-$B44)/(1-Weights!$C$5-Weights!$C$7))*($B$6-Weights!$C$5*Scoring!D$25-Weights!$C$7*Scoring!D$27) -> 27.803164 | E44: =$A44*Scoring!E$25+$B44*Scoring!E$27+((1-$A44-$B44)/(1-Weights!$C$5-Weights!$C$7))*($B$7-Weights!$C$5*Scoring!E$25-Weights!$C$7*Scoring!E$27) -> 40.792195 | F44: =$A44*Scoring!F$25+$B44*Scoring!F$27+((1-$A44-$B44)/(1-Weights!$C$5-Weights!$C$7))*($B$8-Weights!$C$5*Scoring!F$25-Weights!$C$7*Scoring!F$27) -> 41.17297 | G44: =$A44*Scoring!G$25+$B44*Scoring!G$27+((1-$A44-$B44)/(1-Weights!$C$5-Weights!$C$7))*($B$9-Weights!$C$5*Scoring!G$25-Weights!$C$7*Scoring!G$27) -> 71.441141 | H44: =$A44*Scoring!H$25+$B44*Scoring!H$27+((1-$A44-$B44)/(1-Weights!$C$5-Weights!$C$7))*($B$10-Weights!$C$5*Scoring!H$25-Weights!$C$7*Scoring!H$27) -> 48.14173 | I44: =INDEX($C$38:$H$38,MATCH(MAX(C44:H44),C44:H44,0)) -> Dallas-Fort Worth, TX
A45: 0.25 | B45: 0.2 | C45: =$A45*Scoring!C$25+$B45*Scoring!C$27+((1-$A45-$B45)/(1-Weights!$C$5-Weights!$C$7))*($B$5-Weights!$C$5*Scoring!C$25-Weights!$C$7*Scoring!C$27) -> 58.529575 | D45: =$A45*Scoring!D$25+$B45*Scoring!D$27+((1-$A45-$B45)/(1-Weights!$C$5-Weights!$C$7))*($B$6-Weights!$C$5*Scoring!D$25-Weights!$C$7*Scoring!D$27) -> 29.735885 | E45: =$A45*Scoring!E$25+$B45*Scoring!E$27+((1-$A45-$B45)/(1-Weights!$C$5-Weights!$C$7))*($B$7-Weights!$C$5*Scoring!E$25-Weights!$C$7*Scoring!E$27) -> 41.783228 | F45: =$A45*Scoring!F$25+$B45*Scoring!F$27+((1-$A45-$B45)/(1-Weights!$C$5-Weights!$C$7))*($B$8-Weights!$C$5*Scoring!F$25-Weights!$C$7*Scoring!F$27) -> 46.517559 | G45: =$A45*Scoring!G$25+$B45*Scoring!G$27+((1-$A45-$B45)/(1-Weights!$C$5-Weights!$C$7))*($B$9-Weights!$C$5*Scoring!G$25-Weights!$C$7*Scoring!G$27) -> 73.053849 | H45: =$A45*Scoring!H$25+$B45*Scoring!H$27+((1-$A45-$B45)/(1-Weights!$C$5-Weights!$C$7))*($B$10-Weights!$C$5*Scoring!H$25-Weights!$C$7*Scoring!H$27) -> 50.419878 | I45: =INDEX($C$38:$H$38,MATCH(MAX(C45:H45),C45:H45,0)) -> Dallas-Fort Worth, TX
A46: 0.25 | B46: 0.3 | C46: =$A46*Scoring!C$25+$B46*Scoring!C$27+((1-$A46-$B46)/(1-Weights!$C$5-Weights!$C$7))*($B$5-Weights!$C$5*Scoring!C$25-Weights!$C$7*Scoring!C$27) -> 55.481301 | D46: =$A46*Scoring!D$25+$B46*Scoring!D$27+((1-$A46-$B46)/(1-Weights!$C$5-Weights!$C$7))*($B$6-Weights!$C$5*Scoring!D$25-Weights!$C$7*Scoring!D$27) -> 31.668607 | E46: =$A46*Scoring!E$25+$B46*Scoring!E$27+((1-$A46-$B46)/(1-Weights!$C$5-Weights!$C$7))*($B$7-Weights!$C$5*Scoring!E$25-Weights!$C$7*Scoring!E$27) -> 42.77426 | F46: =$A46*Scoring!F$25+$B46*Scoring!F$27+((1-$A46-$B46)/(1-Weights!$C$5-Weights!$C$7))*($B$8-Weights!$C$5*Scoring!F$25-Weights!$C$7*Scoring!F$27) -> 51.862148 | G46: =$A46*Scoring!G$25+$B46*Scoring!G$27+((1-$A46-$B46)/(1-Weights!$C$5-Weights!$C$7))*($B$9-Weights!$C$5*Scoring!G$25-Weights!$C$7*Scoring!G$27) -> 74.666556 | H46: =$A46*Scoring!H$25+$B46*Scoring!H$27+((1-$A46-$B46)/(1-Weights!$C$5-Weights!$C$7))*($B$10-Weights!$C$5*Scoring!H$25-Weights!$C$7*Scoring!H$27) -> 52.698027 | I46: =INDEX($C$38:$H$38,MATCH(MAX(C46:H46),C46:H46,0)) -> Dallas-Fort Worth, TX
A47: 0.35 | B47: 0.05 | C47: =$A47*Scoring!C$25+$B47*Scoring!C$27+((1-$A47-$B47)/(1-Weights!$C$5-Weights!$C$7))*($B$5-Weights!$C$5*Scoring!C$25-Weights!$C$7*Scoring!C$27) -> 64.855088 | D47: =$A47*Scoring!D$25+$B47*Scoring!D$27+((1-$A47-$B47)/(1-Weights!$C$5-Weights!$C$7))*($B$6-Weights!$C$5*Scoring!D$25-Weights!$C$7*Scoring!D$27) -> 29.915866 | E47: =$A47*Scoring!E$25+$B47*Scoring!E$27+((1-$A47-$B47)/(1-Weights!$C$5-Weights!$C$7))*($B$7-Weights!$C$5*Scoring!E$25-Weights!$C$7*Scoring!E$27) -> 40.595548 | F47: =$A47*Scoring!F$25+$B47*Scoring!F$27+((1-$A47-$B47)/(1-Weights!$C$5-Weights!$C$7))*($B$8-Weights!$C$5*Scoring!F$25-Weights!$C$7*Scoring!F$27) -> 35.223558 | G47: =$A47*Scoring!G$25+$B47*Scoring!G$27+((1-$A47-$B47)/(1-Weights!$C$5-Weights!$C$7))*($B$9-Weights!$C$5*Scoring!G$25-Weights!$C$7*Scoring!G$27) -> 72.157663 | H47: =$A47*Scoring!H$25+$B47*Scoring!H$27+((1-$A47-$B47)/(1-Weights!$C$5-Weights!$C$7))*($B$10-Weights!$C$5*Scoring!H$25-Weights!$C$7*Scoring!H$27) -> 44.460682 | I47: =INDEX($C$38:$H$38,MATCH(MAX(C47:H47),C47:H47,0)) -> Dallas-Fort Worth, TX
A48: 0.35 | B48: 0.1 | C48: =$A48*Scoring!C$25+$B48*Scoring!C$27+((1-$A48-$B48)/(1-Weights!$C$5-Weights!$C$7))*($B$5-Weights!$C$5*Scoring!C$25-Weights!$C$7*Scoring!C$27) -> 63.330951 | D48: =$A48*Scoring!D$25+$B48*Scoring!D$27+((1-$A48-$B48)/(1-Weights!$C$5-Weights!$C$7))*($B$6-Weights!$C$5*Scoring!D$25-Weights!$C$7*Scoring!D$27) -> 30.882227 | E48: =$A48*Scoring!E$25+$B48*Scoring!E$27+((1-$A48-$B48)/(1-Weights!$C$5-Weights!$C$7))*($B$7-Weights!$C$5*Scoring!E$25-Weights!$C$7*Scoring!E$27) -> 41.091065 | F48: =$A48*Scoring!F$25+$B48*Scoring!F$27+((1-$A48-$B48)/(1-Weights!$C$5-Weights!$C$7))*($B$8-Weights!$C$5*Scoring!F$25-Weights!$C$7*Scoring!F$27) -> 37.895852 | G48: =$A48*Scoring!G$25+$B48*Scoring!G$27+((1-$A48-$B48)/(1-Weights!$C$5-Weights!$C$7))*($B$9-Weights!$C$5*Scoring!G$25-Weights!$C$7*Scoring!G$27) -> 72.964017 | H48: =$A48*Scoring!H$25+$B48*Scoring!H$27+((1-$A48-$B48)/(1-Weights!$C$5-Weights!$C$7))*($B$10-Weights!$C$5*Scoring!H$25-Weights!$C$7*Scoring!H$27) -> 45.599756 | I48: =INDEX($C$38:$H$38,MATCH(MAX(C48:H48),C48:H48,0)) -> Dallas-Fort Worth, TX
A49: 0.35 | B49: 0.2 | C49: =$A49*Scoring!C$25+$B49*Scoring!C$27+((1-$A49-$B49)/(1-Weights!$C$5-Weights!$C$7))*($B$5-Weights!$C$5*Scoring!C$25-Weights!$C$7*Scoring!C$27) -> 60.282677 | D49: =$A49*Scoring!D$25+$B49*Scoring!D$27+((1-$A49-$B49)/(1-Weights!$C$5-Weights!$C$7))*($B$6-Weights!$C$5*Scoring!D$25-Weights!$C$7*Scoring!D$27) -> 32.814948 | E49: =$A49*Scoring!E$25+$B49*Scoring!E$27+((1-$A49-$B49)/(1-Weights!$C$5-Weights!$C$7))*($B$7-Weights!$C$5*Scoring!E$25-Weights!$C$7*Scoring!E$27) -> 42.082097 | F49: =$A49*Scoring!F$25+$B49*Scoring!F$27+((1-$A49-$B49)/(1-Weights!$C$5-Weights!$C$7))*($B$8-Weights!$C$5*Scoring!F$25-Weights!$C$7*Scoring!F$27) -> 43.240441 | G49: =$A49*Scoring!G$25+$B49*Scoring!G$27+((1-$A49-$B49)/(1-Weights!$C$5-Weights!$C$7))*($B$9-Weights!$C$5*Scoring!G$25-Weights!$C$7*Scoring!G$27) -> 74.576724 | H49: =$A49*Scoring!H$25+$B49*Scoring!H$27+((1-$A49-$B49)/(1-Weights!$C$5-Weights!$C$7))*($B$10-Weights!$C$5*Scoring!H$25-Weights!$C$7*Scoring!H$27) -> 47.877905 | I49: =INDEX($C$38:$H$38,MATCH(MAX(C49:H49),C49:H49,0)) -> Dallas-Fort Worth, TX
A50: 0.35 | B50: 0.3 | C50: =$A50*Scoring!C$25+$B50*Scoring!C$27+((1-$A50-$B50)/(1-Weights!$C$5-Weights!$C$7))*($B$5-Weights!$C$5*Scoring!C$25-Weights!$C$7*Scoring!C$27) -> 57.234403 | D50: =$A50*Scoring!D$25+$B50*Scoring!D$27+((1-$A50-$B50)/(1-Weights!$C$5-Weights!$C$7))*($B$6-Weights!$C$5*Scoring!D$25-Weights!$C$7*Scoring!D$27) -> 34.74767 | E50: =$A50*Scoring!E$25+$B50*Scoring!E$27+((1-$A50-$B50)/(1-Weights!$C$5-Weights!$C$7))*($B$7-Weights!$C$5*Scoring!E$25-Weights!$C$7*Scoring!E$27) -> 43.073129 | F50: =$A50*Scoring!F$25+$B50*Scoring!F$27+((1-$A50-$B50)/(1-Weights!$C$5-Weights!$C$7))*($B$8-Weights!$C$5*Scoring!F$25-Weights!$C$7*Scoring!F$27) -> 48.58503 | G50: =$A50*Scoring!G$25+$B50*Scoring!G$27+((1-$A50-$B50)/(1-Weights!$C$5-Weights!$C$7))*($B$9-Weights!$C$5*Scoring!G$25-Weights!$C$7*Scoring!G$27) -> 76.189431 | H50: =$A50*Scoring!H$25+$B50*Scoring!H$27+((1-$A50-$B50)/(1-Weights!$C$5-Weights!$C$7))*($B$10-Weights!$C$5*Scoring!H$25-Weights!$C$7*Scoring!H$27) -> 50.156053 | I50: =INDEX($C$38:$H$38,MATCH(MAX(C50:H50),C50:H50,0)) -> Dallas-Fort Worth, TX
... A54: 0.45 | B54: 0.3 | C54: =$A54*Scoring!C$25+$B54*Scoring!C$27+((1-$A54-$B54)/(1-Weights!$C$5-Weights!$C$7))*($B$5-Weights!$C$5*Scoring!C$25-Weights!$C$7*Scoring!C$27) -> 58.987506 | D54: =$A54*Scoring!D$25+$B54*Scoring!D$27+((1-$A54-$B54)/(1-Weights!$C$5-Weights!$C$7))*($B$6-Weights!$C$5*Scoring!D$25-Weights!$C$7*Scoring!D$27) -> 37.826733 | E54: =$A54*Scoring!E$25+$B54*Scoring!E$27+((1-$A54-$B54)/(1-Weights!$C$5-Weights!$C$7))*($B$7-Weights!$C$5*Scoring!E$25-Weights!$C$7*Scoring!E$27) -> 43.371999 | F54: =$A54*Scoring!F$25+$B54*Scoring!F$27+((1-$A54-$B54)/(1-Weights!$C$5-Weights!$C$7))*($B$8-Weights!$C$5*Scoring!F$25-Weights!$C$7*Scoring!F$27) -> 45.307913 | G54: =$A54*Scoring!G$25+$B54*Scoring!G$27+((1-$A54-$B54)/(1-Weights!$C$5-Weights!$C$7))*($B$9-Weights!$C$5*Scoring!G$25-Weights!$C$7*Scoring!G$27) -> 77.712307 | H54: =$A54*Scoring!H$25+$B54*Scoring!H$27+((1-$A54-$B54)/(1-Weights!$C$5-Weights!$C$7))*($B$10-Weights!$C$5*Scoring!H$25-Weights!$C$7*Scoring!H$27) -> 47.61408 | I54: =INDEX($C$38:$H$38,MATCH(MAX(C54:H54),C54:H54,0)) -> Dallas-Fort Worth, TX
A57: Leader matrix (rows = Power weight, columns = Network & Latency weight)
A58: Power \ Latency | B58: =B39 -> 0.05 | C58: =B40 -> 0.1 | D58: =B41 -> 0.2 | E58: =B42 -> 0.3
A59: =A39 -> 0.15 | B59: =I39 -> Dallas-Fort Worth, TX | C59: =I40 -> Dallas-Fort Worth, TX | D59: =I41 -> Dallas-Fort Worth, TX | E59: =I42 -> Dallas-Fort Worth, TX
A60: =A43 -> 0.25 | B60: =I43 -> Dallas-Fort Worth, TX | C60: =I44 -> Dallas-Fort Worth, TX | D60: =I45 -> Dallas-Fort Worth, TX | E60: =I46 -> Dallas-Fort Worth, TX
A61: =A47 -> 0.35 | B61: =I47 -> Dallas-Fort Worth, TX | C61: =I48 -> Dallas-Fort Worth, TX | D61: =I49 -> Dallas-Fort Worth, TX | E61: =I50 -> Dallas-Fort Worth, TX
A62: =A51 -> 0.45 | B62: =I51 -> Dallas-Fort Worth, TX | C62: =I52 -> Dallas-Fort Worth, TX | D62: =I53 -> Dallas-Fort Worth, TX | E62: =I54 -> Dallas-Fort Worth, TX

Sheet Latency
A1: Latency estimate - population-weighted fiber round-trip time
A2: Physics-based estimate only (great-circle distance x route factor / speed of light in fiber). Not measured. Blue cells are editable.
A4: Fiber route factor (route length / straight-line) | B4: 1.5 | C4: Assumption: real fiber routes typically run 1.3-1.6x the straight-line distance.
A5: Signal speed in fiber (km per ms, one way) | B5: 200 | C5: Assumption: light travels about 200,000 km/s in glass (about 5 microseconds per km).
A8: Site coordinates are in F15:K16 (blue). Metro table below.
E14: Site | F14: Seattle / Quincy, WA | G14: Hillsboro / Portland, OR | H14: Phoenix, AZ | I14: Northern Virginia | J14: Dallas-Fort Worth, TX | K14: Columbus, OH
A15: Latitude | E15: Latitude | F15: 47.23 | G15: 45.52 | H15: 33.45 | I15: 39.04 | J15: 32.78 | K15: 39.96
A16: Longitude | E16: Longitude | F16: -119.85 | G16: -122.99 | H16: -112.07 | I16: -77.49 | J16: -96.8 | K16: -83
A17: Metro | B17: Lat | C17: Lon | D17: Pop. (M, approx.) | E17: Metro (RTT in ms) / Site | F17: Quincy, WA | G17: Hillsboro, OR | H17: Phoenix, AZ | I17: Ashburn, VA | J17: Dallas, TX | K17: Columbus, OH
A18: New York | B18: 40.71 | C18: -74.01 | D18: 19.5 | F18: =2*(2*6371*ASIN(SQRT(SIN(RADIANS(F$15-$B18)/2)^2+COS(RADIANS($B18))*COS(RADIANS(F$15))*SIN(RADIANS(F$16-$C18)/2)^2)))*$B$4/$B$5 -> 55.265151 | G18: =2*(2*6371*ASIN(SQRT(SIN(RADIANS(G$15-$B18)/2)^2+COS(RADIANS($B18))*COS(RADIANS(G$15))*SIN(RADIANS(G$16-$C18)/2)^2)))*$B$4/$B$5 -> 59.239193 | H18: =2*(2*6371*ASIN(SQRT(SIN(RADIANS(H$15-$B18)/2)^2+COS(RADIANS($B18))*COS(RADIANS(H$15))*SIN(RADIANS(H$16-$C18)/2)^2)))*$B$4/$B$5 -> 51.644139 | I18: =2*(2*6371*ASIN(SQRT(SIN(RADIANS(I$15-$B18)/2)^2+COS(RADIANS($B18))*COS(RADIANS(I$15))*SIN(RADIANS(I$16-$C18)/2)^2)))*$B$4/$B$5 -> 5.2530654 | J18: =2*(2*6371*ASIN(SQRT(SIN(RADIANS(J$15-$B18)/2)^2+COS(RADIANS($B18))*COS(RADIANS(J$15))*SIN(RADIANS(J$16-$C18)/2)^2)))*$B$4/$B$5 -> 33.080626 | K18: =2*(2*6371*ASIN(SQRT(SIN(RADIANS(K$15-$B18)/2)^2+COS(RADIANS($B18))*COS(RADIANS(K$15))*SIN(RADIANS(K$16-$C18)/2)^2)))*$B$4/$B$5 -> 11.493112
A19: Los Angeles | B19: 34.05 | C19: -118.24 | D19: 12.8 | F19: =2*(2*6371*ASIN(SQRT(SIN(RADIANS(F$15-$B19)/2)^2+COS(RADIANS($B19))*COS(RADIANS(F$15))*SIN(RADIANS(F$16-$C19)/2)^2)))*$B$4/$B$5 -> 22.076137 | G19: =2*(2*6371*ASIN(SQRT(SIN(RADIANS(G$15-$B19)/2)^2+COS(RADIANS($B19))*COS(RADIANS(G$15))*SIN(RADIANS(G$16-$C19)/2)^2)))*$B$4/$B$5 -> 20.06672 | H19: =2*(2*6371*ASIN(SQRT(SIN(RADIANS(H$15-$B19)/2)^2+COS(RADIANS($B19))*COS(RADIANS(H$15))*SIN(RADIANS(H$16-$C19)/2)^2)))*$B$4/$B$5 -> 8.6136926 | I19: =2*(2*6371*ASIN(SQRT(SIN(RADIANS(I$15-$B19)/2)^2+COS(RADIANS($B19))*COS(RADIANS(I$15))*SIN(RADIANS(I$16-$C19)/2)^2)))*$B$4/$B$5 -> 54.773711 | J19: =2*(2*6371*ASIN(SQRT(SIN(RADIANS(J$15-$B19)/2)^2+COS(RADIANS($B19))*COS(RADIANS(J$15))*SIN(RADIANS(J$16-$C19)/2)^2)))*$B$4/$B$5 -> 29.869731 | K19: =2*(2*6371*ASIN(SQRT(SIN(RADIANS(K$15-$B19)/2)^2+COS(RADIANS($B19))*COS(RADIANS(K$15))*SIN(RADIANS(K$16-$C19)/2)^2)))*$B$4/$B$5 -> 47.638884
A20: Chicago | B20: 41.88 | C20: -87.63 | D20: 9.3 | F20: =2*(2*6371*ASIN(SQRT(SIN(RADIANS(F$15-$B20)/2)^2+COS(RADIANS($B20))*COS(RADIANS(F$15))*SIN(RADIANS(F$16-$C20)/2)^2)))*$B$4/$B$5 -> 39.021698 | G20: =2*(2*6371*ASIN(SQRT(SIN(RADIANS(G$15-$B20)/2)^2+COS(RADIANS($B20))*COS(RADIANS(G$15))*SIN(RADIANS(G$16-$C20)/2)^2)))*$B$4/$B$5 -> 42.716943 | H20: =2*(2*6371*ASIN(SQRT(SIN(RADIANS(H$15-$B20)/2)^2+COS(RADIANS($B20))*COS(RADIANS(H$15))*SIN(RADIANS(H$16-$C20)/2)^2)))*$B$4/$B$5 -> 35.039582 | I20: =2*(2*6371*ASIN(SQRT(SIN(RADIANS(I$15-$B20)/2)^2+COS(RADIANS($B20))*COS(RADIANS(I$15))*SIN(RADIANS(I$16-$C20)/2)^2)))*$B$4/$B$5 -> 13.701795 | J20: =2*(2*6371*ASIN(SQRT(SIN(RADIANS(J$15-$B20)/2)^2+COS(RADIANS($B20))*COS(RADIANS(J$15))*SIN(RADIANS(J$16-$C20)/2)^2)))*$B$4/$B$5 -> 19.424554 | K20: =2*(2*6371*ASIN(SQRT(SIN(RADIANS(K$15-$B20)/2)^2+COS(RADIANS($B20))*COS(RADIANS(K$15))*SIN(RADIANS(K$16-$C20)/2)^2)))*$B$4/$B$5 -> 6.6549157
A21: Dallas-Fort Worth | B21: 32.78 | C21: -96.8 | D21: 8.1 | F21: =2*(2*6371*ASIN(SQRT(SIN(RADIANS(F$15-$B21)/2)^2+COS(RADIANS($B21))*COS(RADIANS(F$15))*SIN(RADIANS(F$16-$C21)/2)^2)))*$B$4/$B$5 -> 37.80057 | G21: =2*(2*6371*ASIN(SQRT(SIN(RADIANS(G$15-$B21)/2)^2+COS(RADIANS($B21))*COS(RADIANS(G$15))*SIN(RADIANS(G$16-$C21)/2)^2)))*$B$4/$B$5 -> 39.710065 | H21: =2*(2*6371*ASIN(SQRT(SIN(RADIANS(H$15-$B21)/2)^2+COS(RADIANS($B21))*COS(RADIANS(H$15))*SIN(RADIANS(H$16-$C21)/2)^2)))*$B$4/$B$5 -> 21.342449 | I21: =2*(2*6371*ASIN(SQRT(SIN(RADIANS(I$15-$B21)/2)^2+COS(RADIANS($B21))*COS(RADIANS(I$15))*SIN(RADIANS(I$16-$C21)/2)^2)))*$B$4/$B$5 -> 28.027395 | J21: =2*(2*6371*ASIN(SQRT(SIN(RADIANS(J$15-$B21)/2)^2+COS(RADIANS($B21))*COS(RADIANS(J$15))*SIN(RADIANS(J$16-$C21)/2)^2)))*$B$4/$B$5 -> 0 | K21: =2*(2*6371*ASIN(SQRT(SIN(RADIANS(K$15-$B21)/2)^2+COS(RADIANS($B21))*COS(RADIANS(K$15))*SIN(RADIANS(K$16-$C21)/2)^2)))*$B$4/$B$5 -> 22.026028
A22: Houston | B22: 29.76 | C22: -95.37 | D22: 7.5 | F22: =2*(2*6371*ASIN(SQRT(SIN(RADIANS(F$15-$B22)/2)^2+COS(RADIANS($B22))*COS(RADIANS(F$15))*SIN(RADIANS(F$16-$C22)/2)^2)))*$B$4/$B$5 -> 42.908613 | G22: =2*(2*6371*ASIN(SQRT(SIN(RADIANS(G$15-$B22)/2)^2+COS(RADIANS($B22))*COS(RADIANS(G$15))*SIN(RADIANS(G$16-$C22)/2)^2)))*$B$4/$B$5 -> 44.592831 | H22: =2*(2*6371*ASIN(SQRT(SIN(RADIANS(H$15-$B22)/2)^2+COS(RADIANS($B22))*COS(RADIANS(H$15))*SIN(RADIANS(H$16-$C22)/2)^2)))*$B$4/$B$5 -> 24.477428 | I22: =2*(2*6371*ASIN(SQRT(SIN(RADIANS(I$15-$B22)/2)^2+COS(RADIANS($B22))*COS(RADIANS(I$15))*SIN(RADIANS(I$16-$C22)/2)^2)))*$B$4/$B$5 -> 28.988084 | J22: =2*(2*6371*ASIN(SQRT(SIN(RADIANS(J$15-$B22)/2)^2+COS(RADIANS($B22))*COS(RADIANS(J$15))*SIN(RADIANS(J$16-$C22)/2)^2)))*$B$4/$B$5 -> 5.4338447 | K22: =2*(2*6371*ASIN(SQRT(SIN(RADIANS(K$15-$B22)/2)^2+COS(RADIANS($B22))*COS(RADIANS(K$15))*SIN(RADIANS(K$16-$C22)/2)^2)))*$B$4/$B$5 -> 23.95467
A23: Washington DC | B23: 38.9 | C23: -77.04 | D23: 6.4 | F23: =2*(2*6371*ASIN(SQRT(SIN(RADIANS(F$15-$B23)/2)^2+COS(RADIANS($B23))*COS(RADIANS(F$15))*SIN(RADIANS(F$16-$C23)/2)^2)))*$B$4/$B$5 -> 53.261085 | G23: =2*(2*6371*ASIN(SQRT(SIN(RADIANS(G$15-$B23)/2)^2+COS(RADIANS($B23))*COS(RADIANS(G$15))*SIN(RADIANS(G$16-$C23)/2)^2)))*$B$4/$B$5 -> 57.026632 | H23: =2*(2*6371*ASIN(SQRT(SIN(RADIANS(H$15-$B23)/2)^2+COS(RADIANS($B23))*COS(RADIANS(H$15))*SIN(RADIANS(H$16-$C23)/2)^2)))*$B$4/$B$5 -> 47.728671 | I23: =2*(2*6371*ASIN(SQRT(SIN(RADIANS(I$15-$B23)/2)^2+COS(RADIANS($B23))*COS(RADIANS(I$15))*SIN(RADIANS(I$16-$C23)/2)^2)))*$B$4/$B$5 -> 0.62853147 | J23: =2*(2*6371*ASIN(SQRT(SIN(RADIANS(J$15-$B23)/2)^2+COS(RADIANS($B23))*COS(RADIANS(J$15))*SIN(RADIANS(J$16-$C23)/2)^2)))*$B$4/$B$5 -> 28.528025 | K23: =2*(2*6371*ASIN(SQRT(SIN(RADIANS(K$15-$B23)/2)^2+COS(RADIANS($B23))*COS(RADIANS(K$15))*SIN(RADIANS(K$16-$C23)/2)^2)))*$B$4/$B$5 -> 7.8775408
A24: Atlanta | B24: 33.75 | C24: -84.39 | D24: 6.3 | F24: =2*(2*6371*ASIN(SQRT(SIN(RADIANS(F$15-$B24)/2)^2+COS(RADIANS($B24))*COS(RADIANS(F$15))*SIN(RADIANS(F$16-$C24)/2)^2)))*$B$4/$B$5 -> 49.711542 | G24: =2*(2*6371*ASIN(SQRT(SIN(RADIANS(G$15-$B24)/2)^2+COS(RADIANS($B24))*COS(RADIANS(G$15))*SIN(RADIANS(G$16-$C24)/2)^2)))*$B$4/$B$5 -> 52.712579 | H24: =2*(2*6371*ASIN(SQRT(SIN(RADIANS(H$15-$B24)/2)^2+COS(RADIANS($B24))*COS(RADIANS(H$15))*SIN(RADIANS(H$16-$C24)/2)^2)))*$B$4/$B$5 -> 38.341286 | I24: =2*(2*6371*ASIN(SQRT(SIN(RADIANS(I$15-$B24)/2)^2+COS(RADIANS($B24))*COS(RADIANS(I$15))*SIN(RADIANS(I$16-$C24)/2)^2)))*$B$4/$B$5 -> 12.785656 | J24: =2*(2*6371*ASIN(SQRT(SIN(RADIANS(J$15-$B24)/2)^2+COS(RADIANS($B24))*COS(RADIANS(J$15))*SIN(RADIANS(J$16-$C24)/2)^2)))*$B$4/$B$5 -> 17.372079 | K24: =2*(2*6371*ASIN(SQRT(SIN(RADIANS(K$15-$B24)/2)^2+COS(RADIANS($B24))*COS(RADIANS(K$15))*SIN(RADIANS(K$16-$C24)/2)^2)))*$B$4/$B$5 -> 10.522188
A25: Philadelphia | B25: 39.95 | C25: -75.17 | D25: 6.2 | F25: =2*(2*6371*ASIN(SQRT(SIN(RADIANS(F$15-$B25)/2)^2+COS(RADIANS($B25))*COS(RADIANS(F$15))*SIN(RADIANS(F$16-$C25)/2)^2)))*$B$4/$B$5 -> 54.539866 | G25: =2*(2*6371*ASIN(SQRT(SIN(RADIANS(G$15-$B25)/2)^2+COS(RADIANS($B25))*COS(RADIANS(G$15))*SIN(RADIANS(G$16-$C25)/2)^2)))*$B$4/$B$5 -> 58.434166 | H25: =2*(2*6371*ASIN(SQRT(SIN(RADIANS(H$15-$B25)/2)^2+COS(RADIANS($B25))*COS(RADIANS(H$15))*SIN(RADIANS(H$16-$C25)/2)^2)))*$B$4/$B$5 -> 50.148704 | I25: =2*(2*6371*ASIN(SQRT(SIN(RADIANS(I$15-$B25)/2)^2+COS(RADIANS($B25))*COS(RADIANS(I$15))*SIN(RADIANS(I$16-$C25)/2)^2)))*$B$4/$B$5 -> 3.3495319 | J25: =2*(2*6371*ASIN(SQRT(SIN(RADIANS(J$15-$B25)/2)^2+COS(RADIANS($B25))*COS(RADIANS(J$15))*SIN(RADIANS(J$16-$C25)/2)^2)))*$B$4/$B$5 -> 31.313757 | K25: =2*(2*6371*ASIN(SQRT(SIN(RADIANS(K$15-$B25)/2)^2+COS(RADIANS($B25))*COS(RADIANS(K$15))*SIN(RADIANS(K$16-$C25)/2)^2)))*$B$4/$B$5 -> 10.007809
A26: Miami | B26: 25.76 | C26: -80.19 | D26: 6.2 | F26: =2*(2*6371*ASIN(SQRT(SIN(RADIANS(F$15-$B26)/2)^2+COS(RADIANS($B26))*COS(RADIANS(F$15))*SIN(RADIANS(F$16-$C26)/2)^2)))*$B$4/$B$5 -> 63.094642 | G26: =2*(2*6371*ASIN(SQRT(SIN(RADIANS(G$15-$B26)/2)^2+COS(RADIANS($B26))*COS(RADIANS(G$15))*SIN(RADIANS(G$16-$C26)/2)^2)))*$B$4/$B$5 -> 65.662144 | H26: =2*(2*6371*ASIN(SQRT(SIN(RADIANS(H$15-$B26)/2)^2+COS(RADIANS($B26))*COS(RADIANS(H$15))*SIN(RADIANS(H$16-$C26)/2)^2)))*$B$4/$B$5 -> 47.768068 | I26: =2*(2*6371*ASIN(SQRT(SIN(RADIANS(I$15-$B26)/2)^2+COS(RADIANS($B26))*COS(RADIANS(I$15))*SIN(RADIANS(I$16-$C26)/2)^2)))*$B$4/$B$5 -> 22.470814 | J26: =2*(2*6371*ASIN(SQRT(SIN(RADIANS(J$15-$B26)/2)^2+COS(RADIANS($B26))*COS(RADIANS(J$15))*SIN(RADIANS(J$16-$C26)/2)^2)))*$B$4/$B$5 -> 26.809311 | K26: =2*(2*6371*ASIN(SQRT(SIN(RADIANS(K$15-$B26)/2)^2+COS(RADIANS($B26))*COS(RADIANS(K$15))*SIN(RADIANS(K$16-$C26)/2)^2)))*$B$4/$B$5 -> 24.005749
A27: Phoenix | B27: 33.45 | C27: -112.07 | D27: 5.1 | F27: =2*(2*6371*ASIN(SQRT(SIN(RADIANS(F$15-$B27)/2)^2+COS(RADIANS($B27))*COS(RADIANS(F$15))*SIN(RADIANS(F$16-$C27)/2)^2)))*$B$4/$B$5 -> 24.990652 | G27: =2*(2*6371*ASIN(SQRT(SIN(RADIANS(G$15-$B27)/2)^2+COS(RADIANS($B27))*COS(RADIANS(G$15))*SIN(RADIANS(G$16-$C27)/2)^2)))*$B$4/$B$5 -> 24.503638 | H27: =2*(2*6371*ASIN(SQRT(SIN(RADIANS(H$15-$B27)/2)^2+COS(RADIANS($B27))*COS(RADIANS(H$15))*SIN(RADIANS(H$16-$C27)/2)^2)))*$B$4/$B$5 -> 0 | I27: =2*(2*6371*ASIN(SQRT(SIN(RADIANS(I$15-$B27)/2)^2+COS(RADIANS($B27))*COS(RADIANS(I$15))*SIN(RADIANS(I$16-$C27)/2)^2)))*$B$4/$B$5 -> 47.146271 | J27: =2*(2*6371*ASIN(SQRT(SIN(RADIANS(J$15-$B27)/2)^2+COS(RADIANS($B27))*COS(RADIANS(J$15))*SIN(RADIANS(J$16-$C27)/2)^2)))*$B$4/$B$5 -> 21.342449 | K27: =2*(2*6371*ASIN(SQRT(SIN(RADIANS(K$15-$B27)/2)^2+COS(RADIANS($B27))*COS(RADIANS(K$15))*SIN(RADIANS(K$16-$C27)/2)^2)))*$B$4/$B$5 -> 40.161049
A28: Boston | B28: 42.36 | C28: -71.06 | D28: 4.9 | F28: =2*(2*6371*ASIN(SQRT(SIN(RADIANS(F$15-$B28)/2)^2+COS(RADIANS($B28))*COS(RADIANS(F$15))*SIN(RADIANS(F$16-$C28)/2)^2)))*$B$4/$B$5 -> 57.362724 | G28: =2*(2*6371*ASIN(SQRT(SIN(RADIANS(G$15-$B28)/2)^2+COS(RADIANS($B28))*COS(RADIANS(G$15))*SIN(RADIANS(G$16-$C28)/2)^2)))*$B$4/$B$5 -> 61.497489 | H28: =2*(2*6371*ASIN(SQRT(SIN(RADIANS(H$15-$B28)/2)^2+COS(RADIANS($B28))*COS(RADIANS(H$15))*SIN(RADIANS(H$16-$C28)/2)^2)))*$B$4/$B$5 -> 55.398163 | I28: =2*(2*6371*ASIN(SQRT(SIN(RADIANS(I$15-$B28)/2)^2+COS(RADIANS($B28))*COS(RADIANS(I$15))*SIN(RADIANS(I$16-$C28)/2)^2)))*$B$4/$B$5 -> 9.8328448 | J28: =2*(2*6371*ASIN(SQRT(SIN(RADIANS(J$15-$B28)/2)^2+COS(RADIANS($B28))*COS(RADIANS(J$15))*SIN(RADIANS(J$16-$C28)/2)^2)))*$B$4/$B$5 -> 37.39573 | K28: =2*(2*6371*ASIN(SQRT(SIN(RADIANS(K$15-$B28)/2)^2+COS(RADIANS($B28))*COS(RADIANS(K$15))*SIN(RADIANS(K$16-$C28)/2)^2)))*$B$4/$B$5 -> 15.503808
A29: San Francisco Bay | B29: 37.77 | C29: -122.42 | D29: 4.6 | F29: =2*(2*6371*ASIN(SQRT(SIN(RADIANS(F$15-$B29)/2)^2+COS(RADIANS($B29))*COS(RADIANS(F$15))*SIN(RADIANS(F$16-$C29)/2)^2)))*$B$4/$B$5 -> 16.089445 | G29: =2*(2*6371*ASIN(SQRT(SIN(RADIANS(G$15-$B29)/2)^2+COS(RADIANS($B29))*COS(RADIANS(G$15))*SIN(RADIANS(G$16-$C29)/2)^2)))*$B$4/$B$5 -> 12.945819 | H29: =2*(2*6371*ASIN(SQRT(SIN(RADIANS(H$15-$B29)/2)^2+COS(RADIANS($B29))*COS(RADIANS(H$15))*SIN(RADIANS(H$16-$C29)/2)^2)))*$B$4/$B$5 -> 15.763098 | I29: =2*(2*6371*ASIN(SQRT(SIN(RADIANS(I$15-$B29)/2)^2+COS(RADIANS($B29))*COS(RADIANS(I$15))*SIN(RADIANS(I$16-$C29)/2)^2)))*$B$4/$B$5 -> 58.159482 | J29: =2*(2*6371*ASIN(SQRT(SIN(RADIANS(J$15-$B29)/2)^2+COS(RADIANS($B29))*COS(RADIANS(J$15))*SIN(RADIANS(J$16-$C29)/2)^2)))*$B$4/$B$5 -> 35.74278 | K29: =2*(2*6371*ASIN(SQRT(SIN(RADIANS(K$15-$B29)/2)^2+COS(RADIANS($B29))*COS(RADIANS(K$15))*SIN(RADIANS(K$16-$C29)/2)^2)))*$B$4/$B$5 -> 50.908052
A30: Seattle | B30: 47.61 | C30: -122.33 | D30: 4.1 | F30: =2*(2*6371*ASIN(SQRT(SIN(RADIANS(F$15-$B30)/2)^2+COS(RADIANS($B30))*COS(RADIANS(F$15))*SIN(RADIANS(F$16-$C30)/2)^2)))*$B$4/$B$5 -> 2.8695317 | G30: =2*(2*6371*ASIN(SQRT(SIN(RADIANS(G$15-$B30)/2)^2+COS(RADIANS($B30))*COS(RADIANS(G$15))*SIN(RADIANS(G$16-$C30)/2)^2)))*$B$4/$B$5 -> 3.567138 | H30: =2*(2*6371*ASIN(SQRT(SIN(RADIANS(H$15-$B30)/2)^2+COS(RADIANS($B30))*COS(RADIANS(H$15))*SIN(RADIANS(H$16-$C30)/2)^2)))*$B$4/$B$5 -> 26.907798 | I30: =2*(2*6371*ASIN(SQRT(SIN(RADIANS(I$15-$B30)/2)^2+COS(RADIANS($B30))*COS(RADIANS(I$15))*SIN(RADIANS(I$16-$C30)/2)^2)))*$B$4/$B$5 -> 55.421541 | J30: =2*(2*6371*ASIN(SQRT(SIN(RADIANS(J$15-$B30)/2)^2+COS(RADIANS($B30))*COS(RADIANS(J$15))*SIN(RADIANS(J$16-$C30)/2)^2)))*$B$4/$B$5 -> 40.54396 | K30: =2*(2*6371*ASIN(SQRT(SIN(RADIANS(K$15-$B30)/2)^2+COS(RADIANS($B30))*COS(RADIANS(K$15))*SIN(RADIANS(K$16-$C30)/2)^2)))*$B$4/$B$5 -> 48.479926
A31: Population-weighted average RTT (ms) | F31: =SUMPRODUCT(F18:F30,$D$18:$D$30)/SUM($D$18:$D$30) -> 41.869701 | G31: =SUMPRODUCT(G18:G30,$D$18:$D$30)/SUM($D$18:$D$30) -> 43.884383 | H31: =SUMPRODUCT(H18:H30,$D$18:$D$30)/SUM($D$18:$D$30) -> 33.742767 | I31: =SUMPRODUCT(I18:I30,$D$18:$D$30)/SUM($D$18:$D$30) -> 23.796483 | J31: =SUMPRODUCT(J18:J30,$D$18:$D$30)/SUM($D$18:$D$30) -> 24.989366 | K31: =SUMPRODUCT(K18:K30,$D$18:$D$30)/SUM($D$18:$D$30) -> 22.724553
A33: Notes: metro populations are rounded approximations of recent Census metro estimates (assumption, blue). Weighting by population assumes users are spread like the US population; a deployment serving a specific region would weight differently.

Sheet MarketFacts
A1: Market facts - qualitative evidence behind the scores (as of Oct 2026)
A2: Not scored directly; supports the rubric scores and the memo. Source IDs refer to the Sources sheet.
A4: Topic | B4: Seattle / Quincy, WA | C4: Hillsboro / Portland, OR | D4: Phoenix, AZ | E4: Northern Virginia | F4: Dallas-Fort Worth, TX | G4: Columbus, OH
A5: Utility / grid | B5: Grant County PUD (Quincy); Seattle City Light / PSE (Seattle core). Western Interconnection; hydro-based. | C5: Portland General Electric (Pacific Power elsewhere in OR). Western Interconnection. | D5: APS and SRP. Desert Southwest. | E5: Dominion Energy Virginia inside PJM. | F5: Oncor and others inside ERCOT. | G5: AEP Ohio inside PJM.
A6: Power queue / availability | B6: Grant PUD: data-center requests above ~900 MW vs roughly 350 MW of uncommitted hydro; load-growth limits and a high-demand tariff (S19, S20). | C6: No facility with >=5 MW contiguous; ~1.0 MW available at YE2025; >90% of 170.3 MW under construction preleased (S5, S6). | D6: APS has not committed to new data-center customers since January 2026; 10-18 GW pending; SRP aims to double generation in 10 years (S24, S25). | E6: Dominion: >40 GW pending requests; up to ~7 years for 100 MW; earliest new blocks late 2028; 10.8 MW available (S2, S11, S13). | F6: ERCOT: ~427-474 GW of large-load requests; Batch Zero study began Sep 2026; 765 MW under construction, ~95% preleased; 3.7 GW planned (S2, S15). | G6: AEP Ohio pipeline fell from roughly 30 GW to 13 GW after tariff; long timelines reported (S12, S18).
A7: Tariff / contract terms | B7: New high-demand industrial tariff at Grant PUD to recover grid upgrade costs (S19). | C7: Schedule 96 (POWER Act): 20 MW+ self-fund distribution, ~90% minimum demand charge; data-center class up ~29.7% (S22, S23). | D7: APS load-commitment agreements; proposed ~45% increase for data-center rate class (S24). | E7: New data-center rate class under review; batch process caps projects at 300 MW (S14, S36). | F7: SB6: $50M security per GW, study fees from $100k, curtailment rights during load shed (S16). | G7: 85% minimum demand, 8-12 year terms, 180 days' notice, study fee $10k-$100k (S17, S18).
A8: Local approvals / moratoria | B8: Seattle paused applications over 20 MVA in 2026; Quincy and Grant County generally pro-development (S19). | C8: Hillsboro 120-day moratorium (July 2026) on new applications (S22). | D8: Municipal restrictions and community opposition narrowing powered-land supply (S2). | E8: Land, permitting and power constraints; community opposition (S2). | F8: Extended rezoning and entitlement timelines (S2). | G8: Some local moratoria; state bills on tariffs and incentives pending (S18).
A9: Tax incentives | B9: New builds still exempt from sales tax on equipment; replacement-equipment exemption repealed Jul 2026 (S21). | C9: HB 4084 temporarily restricts enterprise-zone property-tax exemption (S2, S35). | D9: 3-year pause on new sales-tax exemption certificates, 1 Jul 2026 to 30 Jun 2029 (S26). | E9: Sales-tax exemption retained in 2026 budget; energy tax added; politically contested (S26, S28). | F9: Exemption intact; repeal flagged as possible 2027 priority (S27, S28). | G9: New exemption applications paused since 27 May 2026; bills pending (S27, S28).
A10: Water / hazard notes | B10: Moderate NRI composite for Grant County; wildfire and air quality are the drivers (S31). | C10: Cascadia seismic risk (analyst note). | D10: WRI 'extremely high' water stress; Maricopa among top-5 NRI counties; Colorado River cuts (S29, S32). | E10: Medium-high seasonal water stress; Potomac supply risk; First Street flags high composite climate risk (S32, S34). | F10: Dallas: top hail risk, top-10 NRI (first release); 2025 flooding hit substations in a major Texas market (S30, S34). | G10: City says supply is ample (S33); tornado and winter-storm exposure (analyst note).
A11: Notable operators / activity | B11: Sabey, Vantage, Microsoft, H5 in Quincy; Sabey 45 MW build-to-suit (S19). | C11: STACK 121 MW expansion; NTT, Flexential, Aligned (S2, S5). | D11: Aligned, QTS, Vantage, STACK, Prime; absorbed 260+ MW in H1 2026 (S2). | E11: STACK 1 GW Stafford campus; AWS land in Loudoun; Digital Realty acquisitions (S2). | F11: Behind-the-meter projects accepted; West Texas emerging as alternative (S2). | G11: Meta, Google, AWS, Microsoft campuses; Meta Prometheus >1 GW in New Albany (S9).

Sheet Sources
A1: Sources
A2: Retrieved 7 Oct 2026. Reliability: High = government/regulator/primary broker; Medium = trade press; Low = aggregators, blogs, derived summaries (verify before relying).
A4: ID | B4: Source | C4: URL | D4: Reliability | E4: Used for
A5: S1 | B5: EIA - Electric Power Annual (2024 data): average revenue per kWh by state | C5: https://www.eia.gov/electricity/Annual/secrev-map.php | D5: High | E5: Industrial power price
A6: S2 | B6: Data Center Frontier - CBRE North America Data Center Trends H1 2026 (28 Aug 2026) | C6: https://www.datacenterfrontier.com/site-selection/news/55401462/cbre-record-data-center-construction-fails-to-ease-capacity-crunch | D6: Medium | E6: Vacancy, availability, construction, moratoria, tax, take-or-pay trends
A7: S3 | B7: CBRE press release - North American demand outpaces supply (H1 2026) | C7: https://www.cbre.com/press-releases/north-american-data-center-demand-continues-to-outpace-supply-despite-record-construction-activity | D7: High | E7: National vacancy, absorption, rents
A8: S4 | B8: CBRE - Global Data Center Trends 2026 | C8: https://www.cbre.com/insights/reports/global-data-center-trends-2026 | D8: High | E8: DFW vacancy 1.8%, NoVA 0.3%, rents
A9: S5 | B9: CBRE - Hillsboro market, H2 2025 (press release) | C9: https://www.cbre.com/press-releases/hillsboro-data-center-market-sees-strong-demand-in-2025-amid-record-national-growth | D9: High | E9: Hillsboro inventory, vacancy, rent range
A10: S6 | B10: CBRE - Hillsboro, OR market page, H1 2026 | C10: https://www.cbre.com/insights/books/north-america-data-center-trends-h1-2026/hillsboro-or-data-center-market | D10: High | E10: Hillsboro 0.21% vacancy, no >=5 MW, 170.3 MW under construction
A11: S7 | B11: JLL - North America Data Center Report, Midyear 2026 | C11: https://www.jll.com/en-us/insights/market-dynamics/north-america-data-centers | D11: High | E11: National vacancy ~1%, frontier markets
A12: S8 | B12: AZ Big Media - JLL Midyear 2025 Phoenix | C12: https://azbigmedia.com/real-estate/big-deals/industrial/phoenix-ranked-no-2-in-us-for-planned-data-center-development/ | D12: Medium | E12: Phoenix vacancy 3%, 31 MW (mid-2025, stale)
A13: S9 | B13: Apollo Technical - Top US data center markets (cites CBRE Q2 2026 and JLL 2026) | C13: https://www.apollotechnical.com/top-data-center-markets/ | D13: Low | E13: DFW 1,432.8 MW / 39.6 MW available; Phoenix 1,069.2 MW; Columbus 0.1% vacancy
A14: S10 | B14: GoDataCenters - Colocation pricing by market 2026 (JLL midyear 2025 ranges) | C14: https://godatacenters.com/blog/colocation-pricing-by-market-2026 | D14: Low | E14: Phoenix, DFW, Columbus rent ranges
A15: S11 | B15: ConstructionOwners - How long it takes to power a data center in 2026 (JLL Outlook) | C15: https://www.constructionowners.com/insights/how-long-it-actually-takes-to-power-a-data-center-in-2026-a-u-s-market-by-market-reality-check | D15: Low | E15: NoVA ~7 yrs, national avg 4 yrs, Phoenix/Columbus context
... A41: S37 | B41: ElectricChoice - data center moratorium tracker | C41: https://www.electricchoice.com/datacenters/moratoriums/ | D41: Low | E41: NOT used in scoring. Lists a Texas action on new grid connections (3 Aug 2026) that could not be verified - see open questions
A43: Not retrieved / gaps
B44: Official FEMA National Risk Index county composite scores (v1.20): the data service was not reachable from this environment; D1 combines NRI-based reporting with analyst scores.
B45: Hillsboro and Seattle/Quincy asking rents and Seattle inventory/vacancy from a primary broker report; Seattle/Quincy rent is an estimate.
B46: Phoenix vacancy is from mid-2025 (JLL); the H1 2026 broker figure was not retrieved.
B47: Market-specific land prices, construction costs, property tax rates, and workforce data were not retrieved and are not scored.
